Workbook

Sheet GESTAO CREDITO E PAGAMENTOS
A1: GESTÃO DE CRÉDITO E PAGAMENTOS 2025 - 2026 | F1: =NOW() -> 46296.634
J2: comparative
A3: INVOICE (EXPORT.) | B3: CUSTOMER | C3: PAIS | D3: ORDER NBR | E3: DATA PROFORM-INVOICE | F3: DATA COLETA (ESTIMADA) | G3: PAYMENT TERMS | H3: days | I3: DATA VENCIMENTO/ DEADLINE | J3: PROFORMA (2026) | K3: DIF PROFORM VS INVOICE FINAL 2026) | L3: TOTAL DUE PAYMENT-AS PER FINAL INVOICE US$ | M3: ADVANCE PAYMENT / FINAL PAYM'T/ NC (US$) | N3: TOTAL DUE BALANCE (US$) | O3: VALOR TOTAL R$ | P3: NÚMERO NF | Q3: STATUS PGTO | R3: OBSERV. | S3: SALES COM. PAID?
A4: 135.24 | B4: DIVINO | D4: 5889 | E4: 45660 | F4: 45660 | G4: 50% Pre Payment - 50% After Received | H4: 30 | I4: =Tabela1[[#This Row],[DATA COLETA (ESTIMADA)]]+Tabela1[[#This Row],[days]] -> 45690 | L4: 22814.54 | M4: 22814.54 | N4: =Tabela1[[#This Row],[ADVANCE PAYMENT / FINAL PAYM''T/ NC (US$)]]-Tabela1[[#This Row],[TOTAL DUE PAYMENT-AS PER FINAL INVOICE US$]] -> 0 | O4: =10017.52+ 74431.82 -> 84449.34 | P4: 56.541 / 56.509 | Q4: paga | R4: PV5321 - NF 56.528 clxd
A5: 136.25 | B5: DIVINO | D5: 5889 | E5: 45679 | F5: 45679 | G5: 50% Pre Payment - 50% After Received | H5: 30 | I5: =Tabela1[[#This Row],[DATA COLETA (ESTIMADA)]]+Tabela1[[#This Row],[days]] -> 45709 | L5: 1623.42 | M5: 1623.42 | N5: =Tabela1[[#This Row],[ADVANCE PAYMENT / FINAL PAYM''T/ NC (US$)]]-Tabela1[[#This Row],[TOTAL DUE PAYMENT-AS PER FINAL INVOICE US$]] -> 0 | O5: 9811.95 | P5: 56691 | Q5: paga
A6: 144.25 | B6: SIMMONS ARGENTINA | C6: ARGENTINA | D6: 6042 | E6: 45659 | F6: 45659 | G6: 30 days after received | H6: 30 | I6: =Tabela1[[#This Row],[DATA COLETA (ESTIMADA)]]+Tabela1[[#This Row],[days]] -> 45689 | L6: 24931.07 | M6: 24931.07 | N6: =Tabela1[[#This Row],[ADVANCE PAYMENT / FINAL PAYM''T/ NC (US$)]]-Tabela1[[#This Row],[TOTAL DUE PAYMENT-AS PER FINAL INVOICE US$]] -> 0 | O6: 153428.31 | P6: 56529 | Q6: paga | U6: Com paga
A7: 145.25 | B7: FLEX CHILE | D7: 6113 | E7: 45665 | F7: 45665 | G7: 90 Days | H7: 90 | I7: =Tabela1[[#This Row],[DATA COLETA (ESTIMADA)]]+Tabela1[[#This Row],[days]] -> 45755 | L7: 6236.148 | M7: 6236.148 | N7: =Tabela1[[#This Row],[ADVANCE PAYMENT / FINAL PAYM''T/ NC (US$)]]-Tabela1[[#This Row],[TOTAL DUE PAYMENT-AS PER FINAL INVOICE US$]] -> 0 | O7: 41965.93 | P7: 56569 | Q7: paga | R7: Paga - sin documentación de soporte
A8: 145.25 | B8: DIVINO | D8: 6039 | E8: 45695 | F8: 45695 | G8: 50% Pre Payment - 50% After Received | H8: 30 | I8: =Tabela1[[#This Row],[DATA COLETA (ESTIMADA)]]+Tabela1[[#This Row],[days]] -> 45725 | L8: 39447.86 | M8: 39447.86 | N8: =Tabela1[[#This Row],[ADVANCE PAYMENT / FINAL PAYM''T/ NC (US$)]]-Tabela1[[#This Row],[TOTAL DUE PAYMENT-AS PER FINAL INVOICE US$]] -> 0 | O8: =220531.08+10617.6 -> 231148.68 | P8: 56.800/56.801 | Q8: paga
A9: 147.25 | B9: PARAISO DEL ECUADOR | C9: ECUADOR | D9: 5929 | E9: 45660 | F9: 45791 | G9: 60 Days | H9: 60 | I9: =Tabela1[[#This Row],[DATA COLETA (ESTIMADA)]]+Tabela1[[#This Row],[days]] -> 45851 | L9: 1302.84 | M9: 1302.84 | N9: =Tabela1[[#This Row],[ADVANCE PAYMENT / FINAL PAYM''T/ NC (US$)]]-Tabela1[[#This Row],[TOTAL DUE PAYMENT-AS PER FINAL INVOICE US$]] -> 0 | O9: 8017.81 | P9: --- | Q9: cancelar | R9: NF 56.540 cxld (8.017,81)- ESCLARECIDO/ Cancelar
A10: 148.25 | B10: SUPERSPUMA PARAGUAY (SAECA) | D10: 6168 | E10: 45677 | F10: 45677 | G10: Pre Payment - 100% Counter Expedition | H10: 0 | I10: =Tabela1[[#This Row],[DATA COLETA (ESTIMADA)]]+Tabela1[[#This Row],[days]] -> 45677 | L10: 6099.58 | M10: 6099.58 | N10: =Tabela1[[#This Row],[ADVANCE PAYMENT / FINAL PAYM''T/ NC (US$)]]-Tabela1[[#This Row],[TOTAL DUE PAYMENT-AS PER FINAL INVOICE US$]] -> 0 | O10: 37706.53 | P10: 56743 | Q10: paga | R10: PV 5165 / 6043 / 5386 - NF 56.544 clxd
A11: 149.25 | B11: SUNLOCK | C11: CHILE | D11: 4645 | E11: 45660 | F11: 45660 | G11: Pre-payment | H11: 0 | I11: =Tabela1[[#This Row],[DATA COLETA (ESTIMADA)]]+Tabela1[[#This Row],[days]] -> 45660 | L11: 2839.2 | M11: 2839.2 | N11: =Tabela1[[#This Row],[ADVANCE PAYMENT / FINAL PAYM''T/ NC (US$)]]-Tabela1[[#This Row],[TOTAL DUE PAYMENT-AS PER FINAL INVOICE US$]] -> 0 | O11: 17472.72 | P11: 56543 | Q11: paga | R11: NF CXLD
A12: 150.25 | B12: DAVID MORENO VISCARRA | D12: 6142 | E12: 45671 | F12: 45687 | G12: 30 days | H12: 30 | I12: =Tabela1[[#This Row],[DATA COLETA (ESTIMADA)]]+Tabela1[[#This Row],[days]] -> 45717 | L12: 4583.75 | M12: =4213.29+370.46 -> 4583.75 | N12: =Tabela1[[#This Row],[ADVANCE PAYMENT / FINAL PAYM''T/ NC (US$)]]-Tabela1[[#This Row],[TOTAL DUE PAYMENT-AS PER FINAL INVOICE US$]] -> 0 | O12: 26858.94 | P12: 56802 | Q12: paga | R12: pgo $15168,15 /enviado cubre 130.24/150.25/157.25
A13: 151.25 | B13: FLEX CHILE | D13: 4725 / 6114 / 6236 | E13: 45686 | F13: 45686 | G13: 90 Days | H13: 90 | I13: =Tabela1[[#This Row],[DATA COLETA (ESTIMADA)]]+Tabela1[[#This Row],[days]] -> 45776 | L13: 13980.26 | M13: 13980.26 | N13: =Tabela1[[#This Row],[ADVANCE PAYMENT / FINAL PAYM''T/ NC (US$)]]-Tabela1[[#This Row],[TOTAL DUE PAYMENT-AS PER FINAL INVOICE US$]] -> 0 | O13: 82385.67 | P13: 56774 | Q13: paga | R13: Notificado/Pgo 03Jun 13980,26
A14: 152.25 | B14: FLEX CHILE | D14: 6114 | E14: 45716 | F14: 45716 | G14: 90 Days | H14: 90 | I14: =Tabela1[[#This Row],[DATA COLETA (ESTIMADA)]]+Tabela1[[#This Row],[days]] -> 45806 | N14: =Tabela1[[#This Row],[ADVANCE PAYMENT / FINAL PAYM''T/ NC (US$)]]-Tabela1[[#This Row],[TOTAL DUE PAYMENT-AS PER FINAL INVOICE US$]] -> 0 | O14: 47380.3 | P14: 57134 | Q14: Não procede | R14: Pedido nunca foi despachado/devem dar baixa do Sistema (US$8137,03/NF R$47380,3)
A15: 153.25 | B15: SUNLOCK | C15: CHILE | D15: 6309 | E15: 45777 | F15: 45803 | G15: 30 days | H15: 30 | I15: =Tabela1[[#This Row],[DATA COLETA (ESTIMADA)]]+Tabela1[[#This Row],[days]] -> 45833 | L15: 3385.14 | M15: 3385.14 | N15: =Tabela1[[#This Row],[ADVANCE PAYMENT / FINAL PAYM''T/ NC (US$)]]-Tabela1[[#This Row],[TOTAL DUE PAYMENT-AS PER FINAL INVOICE US$]] -> 0 | O15: 15748.19 | P15: 57899 | Q15: paga | R15: cliente notificado 1/7 - sem resposta --25/08 / NF 153- Invoice 157- SWIFT recibido 12/09- PROBLEMAS DE QA
A16: 156.25 | B16: DIVINO | D16: 6353 | E16: 45716 | F16: 45716 | G16: 50% Pre Payment - 50% After Received | H16: 30 | I16: =Tabela1[[#This Row],[DATA COLETA (ESTIMADA)]]+Tabela1[[#This Row],[days]] -> 45746 | L16: 42371.047 | M16: 42371.047 | N16: =Tabela1[[#This Row],[ADVANCE PAYMENT / FINAL PAYM''T/ NC (US$)]]-Tabela1[[#This Row],[TOTAL DUE PAYMENT-AS PER FINAL INVOICE US$]] -> 0 | O16: 246718.14 | P16: 57145 | Q16: paga
A17: 157.25 | B17: DAVID MORENO VISCARRA | D17: 6384 | E17: 45701 | F17: 45726 | G17: 30 days | H17: 30 | I17: =Tabela1[[#This Row],[DATA COLETA (ESTIMADA)]]+Tabela1[[#This Row],[days]] -> 45756 | L17: 10252.8 | M17: 10252.8 | N17: =Tabela1[[#This Row],[ADVANCE PAYMENT / FINAL PAYM''T/ NC (US$)]]-Tabela1[[#This Row],[TOTAL DUE PAYMENT-AS PER FINAL INVOICE US$]] -> 0 | O17: =27860.93+32462.42 -> 60323.35 | P17: 57600/57.144 | Q17: paga | R17: pgo $15168,15 /enviado cubre 130.24/150.25/157.25
A18: 157.25 | B18: SUNLOCK | C18: CHILE | D18: 6309 | E18: 45741 | F18: 45741 | G18: 30 days | H18: 30 | I18: =Tabela1[[#This Row],[DATA COLETA (ESTIMADA)]]+Tabela1[[#This Row],[days]] -> 45771 | L18: 5271.96 | M18: 5271.96 | N18: =Tabela1[[#This Row],[ADVANCE PAYMENT / FINAL PAYM''T/ NC (US$)]]-Tabela1[[#This Row],[TOTAL DUE PAYMENT-AS PER FINAL INVOICE US$]] -> 0 | O18: 24559.87 | P18: 57401 | Q18: paga | R18: pgto 13Jun VALOR DE FRETE:R$ 5.702,75/ NF 57.397 cxld/ não tem pasta
A19: 158.25 | B19: SUPERSPUMA PARAGUAY (SAECA) | D19: 6310 | E19: 45741 | F19: 45741 | G19: Pre Payment - 100% Counter Expedition | H19: 0 | I19: =Tabela1[[#This Row],[DATA COLETA (ESTIMADA)]]+Tabela1[[#This Row],[days]] -> 45741 | L19: 3483.0436 | M19: 3483.0436 | N19: =Tabela1[[#This Row],[ADVANCE PAYMENT / FINAL PAYM''T/ NC (US$)]]-Tabela1[[#This Row],[TOTAL DUE PAYMENT-AS PER FINAL INVOICE US$]] -> 0 | O19: 19993.72 | P19: 57396 | Q19: paga
A20: 159.25 | B20: DIVINO | D20: 6623 / 6561 | E20: 45743 | F20: 45769 | G20: 50% Pre Payment - 50% After Received | H20: 30 | I20: =Tabela1[[#This Row],[DATA COLETA (ESTIMADA)]]+Tabela1[[#This Row],[days]] -> 45799 | L20: 50430.38 | M20: 50430.38 | N20: =Tabela1[[#This Row],[ADVANCE PAYMENT / FINAL PAYM''T/ NC (US$)]]-Tabela1[[#This Row],[TOTAL DUE PAYMENT-AS PER FINAL INVOICE US$]] -> 0 | O20: 295315.24 | P20: 57746 | Q20: paga | R20: PV 6623 / 6561
A21: 159.25 | B21: PARAISO DEL ECUADOR | C21: ECUADOR | D21: 6536 / 6827 | E21: 45761 | F21: 45791 | G21: 60 Days | H21: 60 | I21: =Tabela1[[#This Row],[DATA COLETA (ESTIMADA)]]+Tabela1[[#This Row],[days]] -> 45851 | L21: 29668.52 | M21: 30363.32 | N21: =Tabela1[[#This Row],[ADVANCE PAYMENT / FINAL PAYM''T/ NC (US$)]]-Tabela1[[#This Row],[TOTAL DUE PAYMENT-AS PER FINAL INVOICE US$]] -> 694.8 | O21: 105997.81 | P21: 57673/57.493 | Q21: paga | R21: faturado - 57652 Devolução? R$ 8017,81-Notificado 13/08/ Swift 30.363,32 (180925)- Recbimento -70 (Taxa)-Consolida 159.25+205.25
A22: 160.25 | B22: DIVINO | D22: 6353 /6561 /6039 /6353 | E22: 45754 | F22: 45754 | G22: 50% Pre Payment - 50% After Received | H22: 30 | I22: =Tabela1[[#This Row],[DATA COLETA (ESTIMADA)]]+Tabela1[[#This Row],[days]] -> 45784 | L22: 55384.55 | M22: 55384.55 | N22: =Tabela1[[#This Row],[ADVANCE PAYMENT / FINAL PAYM''T/ NC (US$)]]-Tabela1[[#This Row],[TOTAL DUE PAYMENT-AS PER FINAL INVOICE US$]] -> 0 | O22: =11933.14+262432.92+9160.55+35911.99 -> 319438.6 | P22: 57492/ 57.489/ 57.559/57.558 | Q22: paga
A23: 161.25 | B23: CUBA - David Rosabal Container 1 | D23: 6732 | E23: 45751 | F23: 45800 | G23: 30 - 60 DAYS | H23: 60 | I23: =Tabela1[[#This Row],[DATA COLETA (ESTIMADA)]]+Tabela1[[#This Row],[days]] -> 45860 | J23: 24544.55 | L23: 51274.55 | M23: =33656.36+4500 -> 38156.36 | N23: =Tabela1[[#This Row],[ADVANCE PAYMENT / FINAL PAYM''T/ NC (US$)]]-Tabela1[[#This Row],[TOTAL DUE PAYMENT-AS PER FINAL INVOICE US$]] -> -13118.19 | O23: 287481.02 | P23: 57547/57553/ 57.566 ajuste | Q23: parcial | R23: 2025-Pending-Ajuste Proforma EUROS (46.557,57)-Sinal US4 4.500 / Revisada para USD/Alinhada com DUE/ Wire Transfer recebido (18226,5)- devolvido -Restricciones cambio- Unifica 161.25 & 162.25
A24: 162.25 | B24: CUBA - David Rosabal Container 2 | D24: 6733/6783 /6782 | E24: 45751 | F24: 45800 | G24: 30 - 60 DAYS | H24: 60 | I24: =Tabela1[[#This Row],[DATA COLETA (ESTIMADA)]]+Tabela1[[#This Row],[days]] -> 45860 | J24: 26730 | N24: =Tabela1[[#This Row],[ADVANCE PAYMENT / FINAL PAYM''T/ NC (US$)]]-Tabela1[[#This Row],[TOTAL DUE PAYMENT-AS PER FINAL INVOICE US$]] -> 0 | O24: 149867.09 | P24: 57547 | Q24: parcial | R24: 2025-Pending-Consolida 162.25 con 161.25- Invoice revisada novamente para USD - Detalhes em Ajustes CubaFile
A25: 163.25 | B25: FLEX CHILE | D25: 6752 / 6868 / 6949 | E25: 45754 | F25: 45792 | G25: 90 Days | H25: 90 | I25: =Tabela1[[#This Row],[DATA COLETA (ESTIMADA)]]+Tabela1[[#This Row],[days]] -> 45882 | N25: =Tabela1[[#This Row],[ADVANCE PAYMENT / FINAL PAYM''T/ NC (US$)]]-Tabela1[[#This Row],[TOTAL DUE PAYMENT-AS PER FINAL INVOICE US$]] -> 0 | O25: - | P25: 58048/57.898 | Q25: paga | R25: 6752 / 6868 / 6949; ajustada para 164.25. Ver valores nessa cell
A26: 163.25 | B26: MAXI KING | D26: 6706 | E26: 45790 | F26: 45793 | G26: 25% Advanced - 2 Cuotes 60/90 | H26: 90 | I26: =Tabela1[[#This Row],[DATA COLETA (ESTIMADA)]]+Tabela1[[#This Row],[days]] -> 45883 | L26: 24721.14 | M26: =4970+10000+9721.14+30 -> 24721.14 | N26: =Tabela1[[#This Row],[ADVANCE PAYMENT / FINAL PAYM''T/ NC (US$)]]-Tabela1[[#This Row],[TOTAL DUE PAYMENT-AS PER FINAL INVOICE US$]] -> 0 | O26: =64073.52+75285.87 -> 139359.39 | P26: 58050/57.900 | Q26: paga | R26: parcialmente atendido .-change in original invoice/not doctd- 3 pgs parciales-Swift filed- -$30
A27: 164.25 | B27: DIVINO | D27: 6816 / 6623 | E27: 45756 | F27: 45786 | G27: 50% Pre Payment - 50% After Received | H27: 30 | I27: =Tabela1[[#This Row],[DATA COLETA (ESTIMADA)]]+Tabela1[[#This Row],[days]] -> 45816 | L27: 63969.62 | M27: 63969.62 | N27: =Tabela1[[#This Row],[ADVANCE PAYMENT / FINAL PAYM''T/ NC (US$)]]-Tabela1[[#This Row],[TOTAL DUE PAYMENT-AS PER FINAL INVOICE US$]] -> 0 | O27: =34858.59+328872.65 -> 363731.24 | P27: 57985 / 57.984 | Q27: paga
A28: 164.25 | B28: SEA TRADING (MATERASSI) | C28: PARAGUAY | D28: 6597 | E28: 45758 | F28: 45758 | G28: Pre-payment | H28: 0 | I28: =Tabela1[[#This Row],[DATA COLETA (ESTIMADA)]]+Tabela1[[#This Row],[days]] -> 45758 | L28: 1610.82 | M28: 1610.82 | N28: =Tabela1[[#This Row],[ADVANCE PAYMENT / FINAL PAYM''T/ NC (US$)]]-Tabela1[[#This Row],[TOTAL DUE PAYMENT-AS PER FINAL INVOICE US$]] -> 0 | O28: 9522.36 | P28: 57657 | Q28: paga
A29: 164.25 | B29: FLEX CHILE | D29: 6752 / 6868 / 6949/6816 /6623 | E29: 45777 | F29: 45792 | G29: 90 Days | H29: 90 | I29: =Tabela1[[#This Row],[DATA COLETA (ESTIMADA)]]+Tabela1[[#This Row],[days]] -> 45882 | L29: 8953.43 | M29: 8953.43 | N29: =Tabela1[[#This Row],[ADVANCE PAYMENT / FINAL PAYM''T/ NC (US$)]]-Tabela1[[#This Row],[TOTAL DUE PAYMENT-AS PER FINAL INVOICE US$]] -> 0 | O29: 23579.07 | P29: 58048 | Q29: paga | R29: Swift pago 07/08- PV 6752 / 6868 / 6949- Consolida 164.24+170.25+176.25- Dev. /57.898/57.985/57.984
A30: 165.25 | B30: INMAPOL | D30: 6495 | E30: 45758 | F30: 45758 | G30: Pre-payment | H30: 0 | I30: =Tabela1[[#This Row],[DATA COLETA (ESTIMADA)]]+Tabela1[[#This Row],[days]] -> 45758 | L30: 6438.41 | M30: =5906+532.41 -> 6438.41 | N30: =Tabela1[[#This Row],[ADVANCE PAYMENT / FINAL PAYM''T/ NC (US$)]]-Tabela1[[#This Row],[TOTAL DUE PAYMENT-AS PER FINAL INVOICE US$]] -> 0 | O30: 38060.65 | P30: 57658 | Q30: paga
A31: 166.25 | B31: FLEX CHILE | D31: 6875 | E31: 45754 | F31: 45771 | G31: 90 Days | H31: 90 | I31: =Tabela1[[#This Row],[DATA COLETA (ESTIMADA)]]+Tabela1[[#This Row],[days]] -> 45861 | L31: 2222.72 | M31: 2222.72 | N31: =Tabela1[[#This Row],[ADVANCE PAYMENT / FINAL PAYM''T/ NC (US$)]]-Tabela1[[#This Row],[TOTAL DUE PAYMENT-AS PER FINAL INVOICE US$]] -> 0 | O31: 12642.83 | P31: 57775 | Q31: cancelar | R31: will NOT Charge--Rep. Qualidade. 2.222,72
A32: 167.25 | B32: FLEX CHILE | D32: 6880/ 7178 | E32: 45769 | F32: 45807 | G32: 90 Days | H32: 90 | I32: =Tabela1[[#This Row],[DATA COLETA (ESTIMADA)]]+Tabela1[[#This Row],[days]] -> 45897 | L32: 12665.19 | M32: 12665.19 | N32: =Tabela1[[#This Row],[ADVANCE PAYMENT / FINAL PAYM''T/ NC (US$)]]-Tabela1[[#This Row],[TOTAL DUE PAYMENT-AS PER FINAL INVOICE US$]] -> 0 | O32: - | P32: 58433/58.358 | Q32: paga | R32: 167+168+/ add +400/+200 dos mesmos artigos 19/5 (125.25 amostras)- SWIFT $12665,19 (030925)- Fup -Invoice saida 167.25+168.25+181.25 +189.25 (12.665,19) -
A33: 168.25 | B33: FLEX CHILE | D33: 6880 / 7015 | E33: 45784 | F33: 45814 | G33: 90 Days | H33: 90 | I33: =Tabela1[[#This Row],[DATA COLETA (ESTIMADA)]]+Tabela1[[#This Row],[days]] -> 45904 | N33: =Tabela1[[#This Row],[ADVANCE PAYMENT / FINAL PAYM''T/ NC (US$)]]-Tabela1[[#This Row],[TOTAL DUE PAYMENT-AS PER FINAL INVOICE US$]] -> 0 | O33: - | P33: - | Q33: paga | R33: 167+168+ - inv 167.25 + 168.25 juntas para faturamento -
A34: 171.25 | B34: DIST. CASEROS | D34: 6881 | E34: 45763 | F34: 45806 | G34: 30 days | H34: 30 | I34: =Tabela1[[#This Row],[DATA COLETA (ESTIMADA)]]+Tabela1[[#This Row],[days]] -> 45836 | L34: =13588.23-2458.33 -> 11129.9 | M34: 11335.23 | N34: =Tabela1[[#This Row],[ADVANCE PAYMENT / FINAL PAYM''T/ NC (US$)]]-Tabela1[[#This Row],[TOTAL DUE PAYMENT-AS PER FINAL INVOICE US$]] -> 205.33 | O34: 77365.96 | P34: 58340 | Q34: paga | R34: faturado 29/05 / cliente notiticado/Frete pago em destino ($2.458,33- R$ 14.791,13 /Swift 0508 (11335,23)
A35: 172.25 | B35: DAVID MORENO VISCARRA | D35: 6882 | E35: 45793 | F35: 45798 | G35: Pre-payment | H35: 0 | I35: =Tabela1[[#This Row],[DATA COLETA (ESTIMADA)]]+Tabela1[[#This Row],[days]] -> 45798 | L35: 5543.9 | M35: =5283.16+260.74 -> 5543.9 | N35: =Tabela1[[#This Row],[ADVANCE PAYMENT / FINAL PAYM''T/ NC (US$)]]-Tabela1[[#This Row],[TOTAL DUE PAYMENT-AS PER FINAL INVOICE US$]] -> 0 | O35: 31389.01 | P35: 58293 | Q35: paga | R35: cliente notificado-Swift recibido 14/08-saldo pendiente
A36: 173.25 | B36: DIVINO | D36: 6816 | E36: 45771 | F36: 45839 | G36: 50% Pre Payment - 50% After Received | H36: 30 | I36: =Tabela1[[#This Row],[DATA COLETA (ESTIMADA)]]+Tabela1[[#This Row],[days]] -> 45869 | L36: 0 | M36: 0 | N36: =Tabela1[[#This Row],[ADVANCE PAYMENT / FINAL PAYM''T/ NC (US$)]]-Tabela1[[#This Row],[TOTAL DUE PAYMENT-AS PER FINAL INVOICE US$]] -> 0 | O36: 0 | P36: 58963 | Q36: cancelar | R36: junto com 177.25 y 184.25 - revisar valor único em 184.25
A37: 174.25 | B37: SUNLOCK SPA | C37: CHILE | D37: 6940 | E37: 45772 | F37: 45817 | G37: 30 days | H37: 30 | I37: =Tabela1[[#This Row],[DATA COLETA (ESTIMADA)]]+Tabela1[[#This Row],[days]] -> 45847 | L37: =13702.88+136.8 -> 13839.68 | M37: =13839.68 -> 13839.68 | N37: =Tabela1[[#This Row],[ADVANCE PAYMENT / FINAL PAYM''T/ NC (US$)]]-Tabela1[[#This Row],[TOTAL DUE PAYMENT-AS PER FINAL INVOICE US$]] -> 0 | O37: 67566.51 | P37: 58356/ 58476 (amostra fat) | Q37: paga | R37: ajuste invoice final. Cliente notificado-NF 58355 devolução venda recusada-Swift 17Oct ($13839.68)/paga amostra 121.25
A38: 175.25 | B38: BED TIME | C38: ARGENTINA | D38: 6954 | E38: 45775 | F38: 45800 | G38: 30 days, after customs clearance | H38: 35 | I38: =Tabela1[[#This Row],[DATA COLETA (ESTIMADA)]]+Tabela1[[#This Row],[days]] -> 45835 | L38: 37823.39 | M38: 37823.39 | N38: =Tabela1[[#This Row],[ADVANCE PAYMENT / FINAL PAYM''T/ NC (US$)]]-Tabela1[[#This Row],[TOTAL DUE PAYMENT-AS PER FINAL INVOICE US$]] -> 0 | O38: 215336.13 | P38: 58275 | Q38: paga | R38: Swift pago 21/7 - faturado; ajuste invoice final. | S38: 2025
A39: 176.25 | B39: FLEX CHILE | D39: 6949 | E39: 45776 | F39: 45792 | G39: 90 Days | H39: 90 | I39: =Tabela1[[#This Row],[DATA COLETA (ESTIMADA)]]+Tabela1[[#This Row],[days]] -> 45882 | N39: =Tabela1[[#This Row],[ADVANCE PAYMENT / FINAL PAYM''T/ NC (US$)]]-Tabela1[[#This Row],[TOTAL DUE PAYMENT-AS PER FINAL INVOICE US$]] -> 0 | O39: - | P39: - | Q39: paga | R39: parcialmente atendido- consolida invoice 164.25
A40: 177.25 | B40: DIVINO | D40: 7068 | E40: 45792 | F40: 45839 | G40: 50% Pre Payment - 50% After Received | H40: 30 | I40: =Tabela1[[#This Row],[DATA COLETA (ESTIMADA)]]+Tabela1[[#This Row],[days]] -> 45869 | L40: 0 | M40: 0 | N40: =Tabela1[[#This Row],[ADVANCE PAYMENT / FINAL PAYM''T/ NC (US$)]]-Tabela1[[#This Row],[TOTAL DUE PAYMENT-AS PER FINAL INVOICE US$]] -> 0 | O40: 0 | P40: 58963 | Q40: cancelar | R40: 177.25+173.25+ 184.25 (consolida saida)- valor em 184.25
A41: 178.25 | B41: =VLOOKUP(Tabela1[[#This Row],[INVOICE (EXPORT.)]],'[1]FOLLOW-UP DIÁRIO PEDIDOS'!$A$5:$S$31,2,0) -> YP S.A. (Grupo Suenolar) | D41: 7095 | E41: 45796 | F41: 45827 | G41: Pre-payment | H41: 0 | I41: =Tabela1[[#This Row],[DATA COLETA (ESTIMADA)]]+Tabela1[[#This Row],[days]] -> 45827 | L41: 1235.39 | M41: =1175.39+60 -> 1235.39 | N41: =Tabela1[[#This Row],[ADVANCE PAYMENT / FINAL PAYM''T/ NC (US$)]]-Tabela1[[#This Row],[TOTAL DUE PAYMENT-AS PER FINAL INVOICE US$]] -> 0 | Q41: paga | R41: 09/06- ajuste de qtde invoice final despacho/pgo 06/06- Taxa $60
A42: 179.25 | B42: SUPERSPUMA PARAGUAY (SAECA) | D42: 7211 | E42: 45805 | F42: 45868 | G42: Pre Payment - 100% Counter Expedition | H42: 0 | I42: =Tabela1[[#This Row],[DATA COLETA (ESTIMADA)]]+Tabela1[[#This Row],[days]] -> 45868 | L42: =11163.27 -> 11163.27 | M42: 11163.27 | N42: =Tabela1[[#This Row],[ADVANCE PAYMENT / FINAL PAYM''T/ NC (US$)]]-Tabela1[[#This Row],[TOTAL DUE PAYMENT-AS PER FINAL INVOICE US$]] -> 0 | O42: 61349.98 | P42: 58807 | Q42: paga | R42: Swift 25/6
A43: 180.25 | B43: =VLOOKUP(Tabela1[[#This Row],[INVOICE (EXPORT.)]],'[1]FOLLOW-UP DIÁRIO PEDIDOS'!$A$5:$S$31,2,0) -> SUNLOCK SPA | C43: CHILE | D43: 7173 | E43: 45805 | F43: 45855 | G43: 30 days | H43: 30 | I43: =Tabela1[[#This Row],[DATA COLETA (ESTIMADA)]]+Tabela1[[#This Row],[days]] -> 45885 | L43: =4134.65+600.29 -> 4734.94 | M43: =3385.14+14591.42 -> 17976.56 | N43: =Tabela1[[#This Row],[ADVANCE PAYMENT / FINAL PAYM''T/ NC (US$)]]-Tabela1[[#This Row],[TOTAL DUE PAYMENT-AS PER FINAL INVOICE US$]] -> 13241.62 | O43: 22640.93 | P43: 58964 | Q43: paga | R43: 2025-Agosto -SWIFT 23/02 (14.591,42) -Ajuste monto invoice final+ Freight (4134,65+600,29)-Aplicar NC x problemas calidad Sertapedic (3.385,14) - NC filed
A44: 181.25 | B44: FLEX CHILE | D44: 7178/6880/7015/7797 | E44: 45806 | F44: 45863 | G44: 90 Days | H44: 90 | I44: =Tabela1[[#This Row],[DATA COLETA (ESTIMADA)]]+Tabela1[[#This Row],[days]] -> 45953 | L44: 11414.39 | M44: 11414.39 | N44: =Tabela1[[#This Row],[ADVANCE PAYMENT / FINAL PAYM''T/ NC (US$)]]-Tabela1[[#This Row],[TOTAL DUE PAYMENT-AS PER FINAL INVOICE US$]] -> 0 | O44: 63051.94 | P44: 59373 | Q44: paga | R44: 181.25+ pendentes anteriores - faturado/ 6880 / 7015 - NF 58965 CXLD - Devoluçao NF59.324 41.676,2/Discrepancia DUE (11441,39) e Invoice (11414,39)-Ordem SWIFT 2710 (11414,39)
A45: 183.25 | B45: FLEX CHILE | D45: (7178 / 7234) | E45: 45810 | F45: 45838 | G45: 90 Days | H45: 90 | I45: =Tabela1[[#This Row],[DATA COLETA (ESTIMADA)]]+Tabela1[[#This Row],[days]] -> 45928 | L45: 11960 | M45: 11960 | N45: =Tabela1[[#This Row],[ADVANCE PAYMENT / FINAL PAYM''T/ NC (US$)]]-Tabela1[[#This Row],[TOTAL DUE PAYMENT-AS PER FINAL INVOICE US$]] -> 0 | O45: 41676.25 | P45: 58965 / 59.324 | Q45: Devolução | R45: (11.960,00) - Devolução cliente processada 23/07 -NF 059.324 - R$ 41.676,25>40.155,07 - NF 58965 Clxd
A46: 184.25 | B46: DIVINO | D46: 7235 (7068 / 7235) | E46: 45810 | F46: 45840 | G46: 50% Pre Payment - 50% After Received | H46: 30 | I46: =Tabela1[[#This Row],[DATA COLETA (ESTIMADA)]]+Tabela1[[#This Row],[days]] -> 45870 | L46: 30148.81 | M46: =17563.81+55+ 12475+55 -> 30148.81 | N46: =Tabela1[[#This Row],[ADVANCE PAYMENT / FINAL PAYM''T/ NC (US$)]]-Tabela1[[#This Row],[TOTAL DUE PAYMENT-AS PER FINAL INVOICE US$]] -> 0 | O46: 165091.87 | P46: 58963 | Q46: paga | R46: despacho junto c/173.25 e 177.25/ Invoice revisada 02Jul -(esta Inv.- 30.148,81)- Swift 11jul 12475 + taxa
A47: 185.25 | B47: INDUCOL | D47: 7442 | E47: 45826 | F47: 45887 | G47: Pre-payment | H47: 0 | I47: =Tabela1[[#This Row],[DATA COLETA (ESTIMADA)]]+Tabela1[[#This Row],[days]] -> 45887 | N47: =Tabela1[[#This Row],[ADVANCE PAYMENT / FINAL PAYM''T/ NC (US$)]]-Tabela1[[#This Row],[TOTAL DUE PAYMENT-AS PER FINAL INVOICE US$]] -> 0 | O47: - | P47: - | Q47: paga | R47: Swift Adv Paymt 23/6- Ojo invoice salida unifica com 193.25
A48: 187.25 | B48: POLYMAX EL GALO | D48: 7523/8302 | E48: 45848 | F48: 45917 | G48: 60 days | H48: 60 | I48: =Tabela1[[#This Row],[DATA COLETA (ESTIMADA)]]+Tabela1[[#This Row],[days]] -> 45977 | J48: 30596 | K48: =Tabela1[[#This Row],[TOTAL DUE PAYMENT-AS PER FINAL INVOICE US$]]/Tabela1[[#This Row],[PROFORMA (2026)]] -> 1.0264868 | L48: =31514.39-108 -> 31406.39 | M48: =15000+7978.5+6978.5+1557.39 -> 31514.39 | N48: =Tabela1[[#This Row],[ADVANCE PAYMENT / FINAL PAYM''T/ NC (US$)]]-Tabela1[[#This Row],[TOTAL DUE PAYMENT-AS PER FINAL INVOICE US$]] -> 108 | O48: =84447.74+88236.97+3428.31+6140.65 -> 182253.67 | P48: 59814 / 59.546/60215 | Q48: paga | R48: 2025-Novembro - enviar consolidado com complemento (15/1)-SWiFT 03Feb26 ($15K) + 18Mar ($7.978,50) + SWIFT 24/03 ($ 6.978,5)+ porción Swift 12/05 abona
A49: 187.25 Final | B49: POLYMAX EL GALO | D49: 7523 | E49: 45962 | F49: 45987 | G49: 60 days | H49: 60 | I49: =Tabela1[[#This Row],[DATA COLETA (ESTIMADA)]]+Tabela1[[#This Row],[days]] -> 46047 | L49: =1144+629.88 -> 1773.88 | M49: =1773.88 -> 1773.88 | N49: =Tabela1[[#This Row],[ADVANCE PAYMENT / FINAL PAYM''T/ NC (US$)]]-Tabela1[[#This Row],[TOTAL DUE PAYMENT-AS PER FINAL INVOICE US$]] -> 0 | O49: 3.428,31/6140,65 | P49: 60215/60627 | Q49: paga | R49: Janeiro26 - invoices x pdtos faltante & reposição qualidade (1.144 + 629,88)- Foi ajustada a data-solic Cliente Via CR (26/11)- Saldo SWIFT12/05 ($6965) abona
A50: 188.25 | B50: DIVINO | D50: 7503 | E50: 45840 | F50: 45871 | G50: 50% Pre Payment - 50% After Received | H50: 30 | I50: =Tabela1[[#This Row],[DATA COLETA (ESTIMADA)]]+Tabela1[[#This Row],[days]] -> 45901 | L50: =60788.5 -> 60788.5 | M50: =29345+55+31333.5+55 -> 60788.5 | N50: =Tabela1[[#This Row],[ADVANCE PAYMENT / FINAL PAYM''T/ NC (US$)]]-Tabela1[[#This Row],[TOTAL DUE PAYMENT-AS PER FINAL INVOICE US$]] -> 0 | O50: =315190.66+10510.17+14187.42 -> 339888.25 | P50: 59540/ 59677/59696 | Q50: paga | R50: Swift 0807-taxa ($55) $29400 )(adiantamento) / Alteração valor proforma por alteração código artigo/juntó saldo de 184.25./Swift 1908 $31388,50/
A51: 189.25 | B51: FLEX CHILE | D51: 7630 | E51: 45848 | F51: 45879 | G51: 90 Days | H51: 90 | I51: =Tabela1[[#This Row],[DATA COLETA (ESTIMADA)]]+Tabela1[[#This Row],[days]] -> 45969 | N51: =Tabela1[[#This Row],[ADVANCE PAYMENT / FINAL PAYM''T/ NC (US$)]]-Tabela1[[#This Row],[TOTAL DUE PAYMENT-AS PER FINAL INVOICE US$]] -> 0 | O51: - | P51: - | Q51: paga | R51: Invoice saida 181.25-167.25
A52: 190.25 | B52: BED TIME | C52: ARGENTINA | D52: 7672/ 8254 | E52: 45852 | F52: 45895 | G52: 60 days, after customs clearance | H52: 70 | I52: =Tabela1[[#This Row],[DATA COLETA (ESTIMADA)]]+Tabela1[[#This Row],[days]] -> 45965 | L52: 43540.78 | M52: 43540.78 | N52: =Tabela1[[#This Row],[ADVANCE PAYMENT / FINAL PAYM''T/ NC (US$)]]-Tabela1[[#This Row],[TOTAL DUE PAYMENT-AS PER FINAL INVOICE US$]] -> 0 | O52: 236827.01 | P52: 60101 | Q52: paga | R52: Ok - SWIFT (26/11) ok - new credit rate- NF 59541 CXLD /NF 59.607 devolução/Faturado 2508/Novo pedido xa refletir credit rate 8254 (anterior Cxld) | S52: 2025
A53: 191.25 | B53: BED TIME | C53: ARGENTINA | D53: 7673 | E53: 45852 | F53: 45967 | G53: 60 days, after customs clearance | H53: 70 | I53: =Tabela1[[#This Row],[DATA COLETA (ESTIMADA)]]+Tabela1[[#This Row],[days]] -> 46037 | L53: 43413.09 | M53: =1547.62+41865.47 -> 43413.09 | N53: =Tabela1[[#This Row],[ADVANCE PAYMENT / FINAL PAYM''T/ NC (US$)]]-Tabela1[[#This Row],[TOTAL DUE PAYMENT-AS PER FINAL INVOICE US$]] -> 0 | O53: 231083.53 | P53: 61051 | Q53: paga | R53: Janeiro26 -ok - new credit rate- entrega para final Outubro / Ajuste Invoice saida/OJO - NC EMITIDA X DIF EN TELAS Y PRECIOS-Aplicar descuento $1.547,62(Taxa credit rate eliminado até 60d)- SWIFT Pgo 03/02 -$41.865,47 | S53: 2025
A54: 192.25 | B54: PARAISO DEL ECUADOR | C54: ECUADOR | D54: 7758 | E54: 45852 | F54: 45897 | G54: 60 Days | H54: 60 | I54: =Tabela1[[#This Row],[DATA COLETA (ESTIMADA)]]+Tabela1[[#This Row],[days]] -> 45957 | J54: 12623.5 | K54: =Tabela1[[#This Row],[TOTAL DUE PAYMENT-AS PER FINAL INVOICE US$]]/Tabela1[[#This Row],[PROFORMA (2026)]] -> 0.9873886 | L54: 12464.3 | M54: 12429.3 | N54: =Tabela1[[#This Row],[ADVANCE PAYMENT / FINAL PAYM''T/ NC (US$)]]-Tabela1[[#This Row],[TOTAL DUE PAYMENT-AS PER FINAL INVOICE US$]] -> -35 | O54: 67578.94 | P54: 60186 | Q54: parcial | R54: 2025 -Outubro- Ok- liberado 23/7-12.623,50-->Ajuste invoice- Notificado- Swift ($12.429,30 - taxa $30) 08/12 | V54: =12623.5-Tabela1[[#This Row],[TOTAL DUE PAYMENT-AS PER FINAL INVOICE US$]] -> 159.2
A55: 193.25 | B55: INDUCOL | D55: 7763/ 8220 | E55: 45852 | F55: 45887 | G55: Pre-payment | H55: 0 | I55: =Tabela1[[#This Row],[DATA COLETA (ESTIMADA)]]+Tabela1[[#This Row],[days]] -> 45887 | L55: 47432.44 | M55: =14020.5+33411.94 -> 47432.44 | N55: =Tabela1[[#This Row],[ADVANCE PAYMENT / FINAL PAYM''T/ NC (US$)]]-Tabela1[[#This Row],[TOTAL DUE PAYMENT-AS PER FINAL INVOICE US$]] -> 0 | O55: 256870.39 | P55: 59929 | Q55: paga | R55: Ok pedido - Invoice unificada com 185.25-incçuye flete /59818 y 59554Clxd- Swift (2008) $33,411.94/ver adelanto em 185.25
A56: 194.25 | B56: SPRINGWALL - VAZQUEZ SACII | D56: 7780/7777/7857 | E56: 45853 | F56: 45876 | G56: 60 Days | H56: 60 | I56: 45967 | L56: 24320 | M56: 24320 | N56: =Tabela1[[#This Row],[ADVANCE PAYMENT / FINAL PAYM''T/ NC (US$)]]-Tabela1[[#This Row],[TOTAL DUE PAYMENT-AS PER FINAL INVOICE US$]] -> 0 | O56: 133278.46 | P56: 59640 | Q56: paga | R56: New credit rate 194.25 + 195.25-Novo pedido 7857 xa diluir credit rate (05/08)/ NF59537 Cxld/Swift recibido 17/10-$24320 ($24290 sin tasa)
A57: 195.25 | B57: SPRINGWALL - VAZQUEZ SACII | D57: 7777 | E57: 45861 | F57: 45891 | G57: 60 Days | H57: 60 | I57: 45967 | N57: =Tabela1[[#This Row],[ADVANCE PAYMENT / FINAL PAYM''T/ NC (US$)]]-Tabela1[[#This Row],[TOTAL DUE PAYMENT-AS PER FINAL INVOICE US$]] -> 0 | O57: --- | P57: --- | Q57: paga | R57: Incluso credit rate - complemento pedido anterior- Consolida Valor em 194.25 (pedido7857)-pago acima documet.
A58: 196.25 | B58: FLEX CHILE | D58: 8123 | E58: 45880 | F58: 45911 | G58: 90 Days | H58: 90 | I58: =Tabela1[[#This Row],[DATA COLETA (ESTIMADA)]]+Tabela1[[#This Row],[days]] -> 46001 | L58: 5506.62 | M58: 5506.62 | N58: =Tabela1[[#This Row],[ADVANCE PAYMENT / FINAL PAYM''T/ NC (US$)]]-Tabela1[[#This Row],[TOTAL DUE PAYMENT-AS PER FINAL INVOICE US$]] -> 0 | O58: 29951.61 | P58: 60119 | Q58: paga | R58: Dezembro - pedido novo - Ok Paga SWIFT 26/11 (5506,62) - Revisar SWIFT 27/10 - Valor $ 11.414,39 - Difiere
A59: 197.25 | B59: DIVINO | D59: 8154 | E59: 45880 | F59: 45922 | G59: 50% Pre Payment - 50% After Received | H59: 30 | I59: =Tabela1[[#This Row],[DATA COLETA (ESTIMADA)]]+Tabela1[[#This Row],[days]] -> 45952 | L59: 19511.33 | M59: =9364+10147.33 -> 19511.33 | N59: =Tabela1[[#This Row],[ADVANCE PAYMENT / FINAL PAYM''T/ NC (US$)]]-Tabela1[[#This Row],[TOTAL DUE PAYMENT-AS PER FINAL INVOICE US$]] -> 0 | O59: =19881.36+84420.36 -> 104301.72 | P59: 60876/60877 | Q59: paga | R59: pedido novo - Ok- 50% Swift pago 15/08 / saldo de 188.25 junto/Swift pgto final 3 oct
A60: 198.25 | B60: SIMMONS ARGENTINA | C60: ARGENTINA | D60: 8172 | E60: 45883 | F60: 45940 | G60: 30 days after received | H60: 30 | I60: =Tabela1[[#This Row],[DATA COLETA (ESTIMADA)]]+Tabela1[[#This Row],[days]] -> 45970 | L60: 33840.5 | M60: 33840.5 | N60: =Tabela1[[#This Row],[ADVANCE PAYMENT / FINAL PAYM''T/ NC (US$)]]-Tabela1[[#This Row],[TOTAL DUE PAYMENT-AS PER FINAL INVOICE US$]] -> 0 | O60: 180129.59 | P60: 61049 | Q60: paga | R60: Novembro - pedido novo - Ok- Ajuste invoice saída- pre-payment/pedido llegó BsAs (21/10)-Pga SWIFT 05/12 | U60: Com paga
A61: 199.25 | B61: SUPERSPUMA PARAGUAY (SAECA) | D61: 8155 | E61: 45881 | F61: 45936 | G61: Pre Payment - 100% Counter Expedition | H61: 0 | I61: =Tabela1[[#This Row],[DATA COLETA (ESTIMADA)]]+Tabela1[[#This Row],[days]] -> 45936 | L61: 14004.62 | M61: 14004.62 | N61: =Tabela1[[#This Row],[ADVANCE PAYMENT / FINAL PAYM''T/ NC (US$)]]-Tabela1[[#This Row],[TOTAL DUE PAYMENT-AS PER FINAL INVOICE US$]] -> 0 | O61: 74545.2 | P61: 61050 | Q61: paga | R61: Outubro - pedido novo - Ok / ajuste invoice saída - coleta 06/10- Swift 02/10 recibido 13/11
A62: 200.25 | B62: MULTIESPUMAS VISCARRA | C62: BOLIVIA | D62: 8315 | E62: 45890 | F62: 45930 | G62: Pre-payment | H62: 0 | I62: =Tabela1[[#This Row],[DATA COLETA (ESTIMADA)]]+Tabela1[[#This Row],[days]] -> 45930 | L62: 16624.3 | M62: 16624.3 | N62: =Tabela1[[#This Row],[ADVANCE PAYMENT / FINAL PAYM''T/ NC (US$)]]-Tabela1[[#This Row],[TOTAL DUE PAYMENT-AS PER FINAL INVOICE US$]] -> 0 | O62: =47291.51+43068.21 -> 90359.72 | P62: 61539/61540 | Q62: paga | R62: Setembro -ok- F-up - Notificado diversas fechas/ OK PAGA SWIFT 12/12/25 | U62: USD | V62: sinal
A63: 201.25 | B63: SERVAN EXPORTADORA DE MANUFACTURADOS LTDA (ABBA) | D63: 8312 | E63: 45894 | F63: 45933 | G63: Pre-payment | H63: 0 | I63: 45981 | L63: =29893.05/5.42 -> 5515.3229 | M63: =29893.05/5.42 -> 5515.3229 | N63: =Tabela1[[#This Row],[ADVANCE PAYMENT / FINAL PAYM''T/ NC (US$)]]-Tabela1[[#This Row],[TOTAL DUE PAYMENT-AS PER FINAL INVOICE US$]] -> 0 | O63: =29893.05-5310 -> 24583.05 | P63: 61146 (R$ 29.893,05) | Q63: paga | R63: Novembro Pgto feito via Boleto -Sinal R$ 5.310,00 (29Ago -Fx 5,41)- Cliente fatura em R$/ R$ 29.893,05 -Invoice inclui Frete R$ 2.483,07 /faturado | T63: Servan | U63: =Tabela1[[#This Row],[TOTAL DUE PAYMENT-AS PER FINAL INVOICE US$]] -> 5515.3229 | V63: =5000/5.42 -> 922.50923 | W63: =U63-V63 -> 4592.8137
A64: 202.25 | B64: DIVINO | D64: 8348 | E64: 45904 | F64: 45936 | G64: 50% Pre Payment - 50% After Received | H64: 30 | I64: =Tabela1[[#This Row],[DATA COLETA (ESTIMADA)]]+Tabela1[[#This Row],[days]] -> 45966 | L64: 11088.02 | M64: =5559+5529.02 -> 11088.02 | N64: =Tabela1[[#This Row],[ADVANCE PAYMENT / FINAL PAYM''T/ NC (US$)]]-Tabela1[[#This Row],[TOTAL DUE PAYMENT-AS PER FINAL INVOICE US$]] -> 0 | O64: =51650+8617.83 -> 60267.83 | P64: 61357/61538 | Q64: paga | R64: Novembro -Swift 50% recebido 23/09-Pronto para coletar (17/10)
A65: 203.25 | B65: INMAPOL | D65: 8353 | E65: 45909 | F65: 45930 | G65: Pre-payment | H65: 0 | I65: =Tabela1[[#This Row],[DATA COLETA (ESTIMADA)]]+Tabela1[[#This Row],[days]] -> 45930 | L65: 6942.6 | M65: 6942.6 | N65: =Tabela1[[#This Row],[ADVANCE PAYMENT / FINAL PAYM''T/ NC (US$)]]-Tabela1[[#This Row],[TOTAL DUE PAYMENT-AS PER FINAL INVOICE US$]] -> 0 | O65: 36954.77 | P65: 61063 | Q65: paga | R65: Ajuste invoice final- Swift pago 07/10
A66: 205.25 | B66: PARAISO DEL ECUADOR | C66: ECUADOR | D66: 8387 | E66: 45912 | F66: 45949 | G66: 30 Days | H66: 30 | I66: =Tabela1[[#This Row],[DATA COLETA (ESTIMADA)]]+Tabela1[[#This Row],[days]] -> 45979 | J66: 694.8 | K66: =Tabela1[[#This Row],[TOTAL DUE PAYMENT-AS PER FINAL INVOICE US$]]/Tabela1[[#This Row],[PROFORMA (2026)]] -> 1.0635003 | L66: 738.92 | M66: 694.8 | N66: =Tabela1[[#This Row],[ADVANCE PAYMENT / FINAL PAYM''T/ NC (US$)]]-Tabela1[[#This Row],[TOTAL DUE PAYMENT-AS PER FINAL INVOICE US$]] -> -44.12 | O66: 3917.02 | P66: 60777 | Q66: parcial | R66: 2025 - Outubro- Inclui frete (334 + 360,80)- Swift 30.363,32 (180925)- Invoice final 738,92 (334 vs. 378,12/ dif de $44,12). Consolida 205.25+159.25-Pgo inferior
A67: 206.25 | B67: FLEX CHILE | D67: 8465 | E67: 45917 | F67: 45952 | G67: 90 Days | H67: 90 | I67: =Tabela1[[#This Row],[DATA COLETA (ESTIMADA)]]+Tabela1[[#This Row],[days]] -> 46042 | L67: 2826 | M67: 2826 | N67: =Tabela1[[#This Row],[ADVANCE PAYMENT / FINAL PAYM''T/ NC (US$)]]-Tabela1[[#This Row],[TOTAL DUE PAYMENT-AS PER FINAL INVOICE US$]] -> 0 | O67: 15215.18 | P67: 61771 | Q67: paga | R67: Janeiro26 -Alteraçao proforma-1item só - paga SWIFT 23/01
A68: 208.25 | B68: FLEX CHILE | D68: 8509 | E68: 45924 | F68: 45926 | G68: 90 Days | H68: 90 | I68: =Tabela1[[#This Row],[DATA COLETA (ESTIMADA)]]+Tabela1[[#This Row],[days]] -> 46016 | L68: 4288.53 | M68: 4288.53 | N68: =Tabela1[[#This Row],[ADVANCE PAYMENT / FINAL PAYM''T/ NC (US$)]]-Tabela1[[#This Row],[TOTAL DUE PAYMENT-AS PER FINAL INVOICE US$]] -> 0 | O68: 22777.24 | P68: 60927 | Q68: paga | R68: Dezembro - Paga SWIFT 06/01 ($4.288,53)
A69: 209.25 | B69: SUNLOCK SPA | C69: CHILE | D69: 8569/8798 | E69: 45925 | F69: 45968 | G69: 30 days | H69: 30 | I69: =Tabela1[[#This Row],[DATA COLETA (ESTIMADA)]]+Tabela1[[#This Row],[days]] -> 45998 | L69: 0 | N69: =Tabela1[[#This Row],[ADVANCE PAYMENT / FINAL PAYM''T/ NC (US$)]]-Tabela1[[#This Row],[TOTAL DUE PAYMENT-AS PER FINAL INVOICE US$]] -> 0 | P69: -- | Q69: paga | R69: Dezembro- consolida em 210.25- SWIFT (23/02) 14.591,42 / SWIFT 24/04/26 $5.659,15 / Revisar o valor a cobrar- NC por problemas de Qualidade ($2.180 Sertapedic -pedido 153.25)-aplicado em invoice vencida-
A70: 210.25 | B70: SUNLOCK SPA | C70: CHILE | D70: 8609 | E70: 45937 | F70: 45968 | G70: 30 days | H70: 30 | I70: =Tabela1[[#This Row],[DATA COLETA (ESTIMADA)]]+Tabela1[[#This Row],[days]] -> 45998 | J70: =4855+8280 -> 13135 | K70: =Tabela1[[#This Row],[TOTAL DUE PAYMENT-AS PER FINAL INVOICE US$]]/Tabela1[[#This Row],[PROFORMA (2026)]] -> 1.0589197 | L70: 13908.91 | M70: =13241.62+5659.15 -> 18900.77 | N70: =Tabela1[[#This Row],[ADVANCE PAYMENT / FINAL PAYM''T/ NC (US$)]]-Tabela1[[#This Row],[TOTAL DUE PAYMENT-AS PER FINAL INVOICE US$]] -> 4991.86 | O70: 73968.98 | P70: 62206 | Q70: paga | R70: Dezembro - Ajuste inv saida/consolida 209.25 + 210.25- Inclui frete / Pago SWIFT (23/02) $14.591,42 (dif luego de pagar 209.25)/ SWIFT 24/04/26 $5.659,15
A71: 211.25 | B71: SUPERSPUMA PARAGUAY (SAECA) | D71: 8614 | E71: 45938 | F71: 45993 | G71: Pre Payment - 100% Counter Expedition | H71: 0 | I71: =Tabela1[[#This Row],[DATA COLETA (ESTIMADA)]]+Tabela1[[#This Row],[days]] -> 45993 | L71: 19504.93 | M71: 19504.93 | N71: =Tabela1[[#This Row],[ADVANCE PAYMENT / FINAL PAYM''T/ NC (US$)]]-Tabela1[[#This Row],[TOTAL DUE PAYMENT-AS PER FINAL INVOICE US$]] -> 0 | P71: 62739 | Q71: paga | R71: Dezembro - Quant aumentadas 07/11- SWIFT 12/12 (19.504,93)
A72: 204.25 | B72: COLCHONES DEL PARAGUAY | D72: 8681 | E72: 45939 | F72: 45980 | G72: Pre-payment | H72: 0 | I72: =Tabela1[[#This Row],[DATA COLETA (ESTIMADA)]]+Tabela1[[#This Row],[days]] -> 45980 | L72: 0 | N72: =Tabela1[[#This Row],[ADVANCE PAYMENT / FINAL PAYM''T/ NC (US$)]]-Tabela1[[#This Row],[TOTAL DUE PAYMENT-AS PER FINAL INVOICE US$]] -> 0 | O72: 0 | P72: -- | Q72: paga | R72: Novembro-Proforma incluye Flete ($ 690)/Swift $2000 (17/10)- carta justificativa-Valor pago-Consolida com 219.25-Swift 4554,95 (27/11)
A73: 213.25 | B73: SIMMONS ARGENTINA | C73: ARGENTINA | D73: 8726 | E73: 45951 | F73: 45999 | G73: 30 days after received | H73: 30 | I73: =Tabela1[[#This Row],[DATA COLETA (ESTIMADA)]]+Tabela1[[#This Row],[days]] -> 46029 | L73: 17776.62 | M73: 17776.62 | N73: =Tabela1[[#This Row],[ADVANCE PAYMENT / FINAL PAYM''T/ NC (US$)]]-Tabela1[[#This Row],[TOTAL DUE PAYMENT-AS PER FINAL INVOICE US$]] -> 0 | O73: 95819.54 | P73: 62567 | Q73: paga | R73: Janeiro26 -proforma nova 21/10- DUE difiere $17.810,82 (amostras? $34,20)-PAGA SWIFT 14Jan26
A74: 214.25 | B74: DIVINO | D74: 9070 | E74: 45951 | F74: 45992 | G74: 50% Pre Payment - 50% After Received | H74: 30 | I74: =Tabela1[[#This Row],[DATA COLETA (ESTIMADA)]]+Tabela1[[#This Row],[days]] -> 46022 | L74: 18180.8 | M74: =9770+8410.8 -> 18180.8 | N74: =Tabela1[[#This Row],[ADVANCE PAYMENT / FINAL PAYM''T/ NC (US$)]]-Tabela1[[#This Row],[TOTAL DUE PAYMENT-AS PER FINAL INVOICE US$]] -> 0 | O74: =96972.75 -> 96972.75 | P74: 62679/62743 | Q74: paga | R74: Dezembro- 50% pago Swift 23/10 - Fup fact 28/11- NF 626709 CXLD / Pgo saldo SWIFT 08/12
A75: 212.25 | B75: FRAZADAS ARTESANALES (LA GRANDE) | C75: PERÚ | D75: 8773/ 9137 | E75: 45950 | F75: 46008 | G75: 30% Pre-Payment - 70% Counter Expedition | H75: 20 | I75: =Tabela1[[#This Row],[DATA COLETA (ESTIMADA)]]+Tabela1[[#This Row],[days]] -> 46028 | J75: 43290 | K75: =Tabela1[[#This Row],[TOTAL DUE PAYMENT-AS PER FINAL INVOICE US$]]/Tabela1[[#This Row],[PROFORMA (2026)]] -> 1.0216735 | L75: 44228.245 | M75: =12987+31096.25 -> 44083.25 | N75: =Tabela1[[#This Row],[ADVANCE PAYMENT / FINAL PAYM''T/ NC (US$)]]-Tabela1[[#This Row],[TOTAL DUE PAYMENT-AS PER FINAL INVOICE US$]] -> -144.995 | O75: =126511.33+241066.1 -> 367577.43 | P75: 62736 / 63143 | Q75: parcial | R75: Jan'26 - Sinal 30% OK (30/10)/Swift final 22/12 ($31.096,25) Underpayment - Proforma ($ 43.290 ) Fup Invoice final ($ 44.228,25 )-67236 Entrada / NF 63097 Cxld-
A76: 215.25 | B76: POLYMAX EL GALO | D76: 8811 | E76: 45964 | F76: 46007 | G76: 60 days | H76: 60 | I76: =Tabela1[[#This Row],[DATA COLETA (ESTIMADA)]]+Tabela1[[#This Row],[days]] -> 46067 | J76: 15055 | K76: =Tabela1[[#This Row],[TOTAL DUE PAYMENT-AS PER FINAL INVOICE US$]]/Tabela1[[#This Row],[PROFORMA (2026)]] -> 0.90856592 | L76: =7880.78+5797.68 -> 13678.46 | M76: =3633.73+10044+0.73 -> 13678.46 | N76: =Tabela1[[#This Row],[ADVANCE PAYMENT / FINAL PAYM''T/ NC (US$)]]-Tabela1[[#This Row],[TOTAL DUE PAYMENT-AS PER FINAL INVOICE US$]] -> 0 | O76: =42752.43+32051.31 -> 74803.74 | P76: 62892/63209 | Q76: paga | R76: Fevereiro'26- Envio parcial 11/12 + seguinte 19/12 (Fup)- sobra SWIFT 12/05 (6965-saldos 187.25+final)/SWIFT 15jun (10.044,00)
A77: 216.25 | B77: DIVINO | D77: 9075 | E77: 45964 | F77: 46006 | G77: 50% Pre Payment - 50% After Received | H77: 30 | I77: =Tabela1[[#This Row],[DATA COLETA (ESTIMADA)]]+Tabela1[[#This Row],[days]] -> 46036 | L77: 20124.81 | M77: =11502.5+8622.31 -> 20124.81 | N77: =Tabela1[[#This Row],[ADVANCE PAYMENT / FINAL PAYM''T/ NC (US$)]]-Tabela1[[#This Row],[TOTAL DUE PAYMENT-AS PER FINAL INVOICE US$]] -> 0 | O77: =34620.28+74196.94 -> 108817.22 | P77: 62680/62891 | Q77: paga | R77: Janeiro26 - Swift 50% recibido (10/11) - Fup fact Dez-> ok- inferior - PGO SWIFT (16/12-$8.622,31)
A78: 217.25 | B78: FLEX CHILE | D78: 8863 | E78: 45971 | F78: 46030 | G78: 90 Days | H78: 90 | I78: =Tabela1[[#This Row],[DATA COLETA (ESTIMADA)]]+Tabela1[[#This Row],[days]] -> 46120 | J78: 6250 | K78: =Tabela1[[#This Row],[TOTAL DUE PAYMENT-AS PER FINAL INVOICE US$]]/Tabela1[[#This Row],[PROFORMA (2026)]] -> 1.037184 | L78: 6482.4 | M78: 6482.4 | N78: =Tabela1[[#This Row],[ADVANCE PAYMENT / FINAL PAYM''T/ NC (US$)]]-Tabela1[[#This Row],[TOTAL DUE PAYMENT-AS PER FINAL INVOICE US$]] -> 0 | O78: 35232.5 | P78: 63251 | Q78: paga | R78: abril'26 -Pick-up 08/01/26 - notificado- SWIFT 10/04 ($6.482,40)
A79: 219.25 | B79: COLCHONES DEL PARAGUAY | D79: 8953 | E79: 45979 | F79: 45980 | G79: Pre-payment | H79: 0 | I79: =Tabela1[[#This Row],[DATA COLETA (ESTIMADA)]]+Tabela1[[#This Row],[days]] -> 45980 | L79: 6554.95 | M79: =2000+4554.95 -> 6554.95 | N79: =Tabela1[[#This Row],[ADVANCE PAYMENT / FINAL PAYM''T/ NC (US$)]]-Tabela1[[#This Row],[TOTAL DUE PAYMENT-AS PER FINAL INVOICE US$]] -> 0 | O79: =12341.34+22463.04 -> 34804.38 | P79: 62468/62395 | Q79: paga | R79: Novembro - ($2112,80) Consolida com 204.25- Material já em stock- inclui frete ($690)- SWIFT 27/11
A80: 220.25 | B80: SUNLOCK SPA | C80: CHILE | D80: 9030 | E80: 45985 | F80: 46010 | G80: 30 days | H80: 30 | I80: =Tabela1[[#This Row],[DATA COLETA (ESTIMADA)]]+Tabela1[[#This Row],[days]] -> 46040 | J80: 14285 | K80: =Tabela1[[#This Row],[TOTAL DUE PAYMENT-AS PER FINAL INVOICE US$]]/Tabela1[[#This Row],[PROFORMA (2026)]] -> 1.104112 | L80: =15772.24 -> 15772.24 | M80: =4991.86+5597.15+5592.15 -> 16181.16 | N80: =Tabela1[[#This Row],[ADVANCE PAYMENT / FINAL PAYM''T/ NC (US$)]]-Tabela1[[#This Row],[TOTAL DUE PAYMENT-AS PER FINAL INVOICE US$]] -> 408.92 | O80: 86999.65 | P80: 63248 | Q80: paga | R80: Janeiro26 - Fup complemento - 14.183,74 + frete 1.588,50 =15.772,24|SWIFT 24/04 ($5.659,15)- abono anterior= diferencia abona parcialmente|SWIFT (01/06) $5.597,15 abono + SWIFT (18/06) $5.592,15-cierra cta y sobra saldo de $346,92 que abona invoice 003.26
A81: 220.25 C | B81: SUNLOCK SPA | C81: CHILE | D81: 9035 | E81: 45985 | F81: 46010 | G81: 30 days | H81: 30 | I81: =Tabela1[[#This Row],[DATA COLETA (ESTIMADA)]]+Tabela1[[#This Row],[days]] -> 46040 | N81: =Tabela1[[#This Row],[ADVANCE PAYMENT / FINAL PAYM''T/ NC (US$)]]-Tabela1[[#This Row],[TOTAL DUE PAYMENT-AS PER FINAL INVOICE US$]] -> 0 | O81: -- | P81: -- | Q81: paga | R81: Janeiro26 - complemento 3 items novos- consolida em 220.25 - ver acima
A82: 218.25 | B82: IMPORTADORA TERRA (MOVELPRO SRL) | C82: BOLIVIA | D82: 9037 | E82: 45988 | F82: 46010 | G82: 30% Pre-Payment - 70% Counter Expedition | H82: 0 | I82: =Tabela1[[#This Row],[DATA COLETA (ESTIMADA)]]+Tabela1[[#This Row],[days]] -> 46010 | L82: 8103.3 | M82: 8618 | N82: =Tabela1[[#This Row],[ADVANCE PAYMENT / FINAL PAYM''T/ NC (US$)]]-Tabela1[[#This Row],[TOTAL DUE PAYMENT-AS PER FINAL INVOICE US$]] -> 514.7 | O82: 44697.82 | P82: 63243 | Q82: paga | R82: Janeiro- Pgto recibido 05/12/overpayment
A83: 221.25 | B83: LAMITEX S.A. | D83: 9125 | E83: 46002 | F83: 46059 | G83: 30% Pre-Payment - 70% Counter Expedition | H83: 0 | I83: =Tabela1[[#This Row],[DATA COLETA (ESTIMADA)]]+Tabela1[[#This Row],[days]] -> 46059 | J83: 23970 | K83: =Tabela1[[#This Row],[TOTAL DUE PAYMENT-AS PER FINAL INVOICE US$]]/Tabela1[[#This Row],[PROFORMA (2026)]] -> 1.0449341 | L83: 25047.07 | M83: =23905+1142.07 -> 25047.07 | N83: =Tabela1[[#This Row],[ADVANCE PAYMENT / FINAL PAYM''T/ NC (US$)]]-Tabela1[[#This Row],[TOTAL DUE PAYMENT-AS PER FINAL INVOICE US$]] -> 0 | O83: 131697.49 | P83: 63819/ 63820 -21 | Q83: paga | R83: fevereiro'26 ( 23.247,07 + frete 1.800 =25.047,05 )-diverg. DUE- Swift (24/02) $23.905,00- dif SWIFT (26/02)1.142,07
A84: 222.25 | B84: FLEX CHILE | C84: CHILE | D84: 9124 | E84: 46002 | F84: 46065 | G84: 90 Days | H84: 90 | I84: =Tabela1[[#This Row],[DATA COLETA (ESTIMADA)]]+Tabela1[[#This Row],[days]] -> 46155 | J84: 2925 | K84: =Tabela1[[#This Row],[TOTAL DUE PAYMENT-AS PER FINAL INVOICE US$]]/Tabela1[[#This Row],[PROFORMA (2026)]] -> 0.95230769 | L84: 2785.5 | M84: 2785.5 | N84: =Tabela1[[#This Row],[ADVANCE PAYMENT / FINAL PAYM''T/ NC (US$)]]-Tabela1[[#This Row],[TOTAL DUE PAYMENT-AS PER FINAL INVOICE US$]] -> 0 | O84: 14593.79 | P84: 63662 | Q84: paga | R84: maio'26 - Pago SWIFT (30/04) $2,785.50
A85: 003.26 | B85: SUNLOCK SPA | C85: CHILE | D85: 9157 | E85: 46010 | F85: 46073 | G85: 30 days | H85: 30 | I85: =Tabela1[[#This Row],[DATA COLETA (ESTIMADA)]]+Tabela1[[#This Row],[days]] -> 46103 | J85: =5170+6490+3874 -> 15534 | K85: =Tabela1[[#This Row],[TOTAL DUE PAYMENT-AS PER FINAL INVOICE US$]]/Tabela1[[#This Row],[PROFORMA (2026)]] -> 1.1705066 | L85: 18182.65 | M85: =408.92+5659.15+21013.51 -> 27081.58 | N85: =Tabela1[[#This Row],[ADVANCE PAYMENT / FINAL PAYM''T/ NC (US$)]]-Tabela1[[#This Row],[TOTAL DUE PAYMENT-AS PER FINAL INVOICE US$]] -> 8898.93 | O85: 95173.45 | P85: 64026 | Q85: parcial | R85: março'26- consolida:003.26+005.26+007.26-Proformas (15.534)-Invoice final (15,282,67 + 2.899,98 frete=18.182,65)/SWIFT 12/08 ($5.659,15)
A86: 004.26 | B86: SIMMONS ARGENTINA | C86: ARGENTINA | D86: 9176 | E86: 46031 | F86: 46087 | G86: 30 days after received | H86: 35 | I86: =Tabela1[[#This Row],[DATA COLETA (ESTIMADA)]]+Tabela1[[#This Row],[days]] -> 46122 | J86: 21960 | K86: =Tabela1[[#This Row],[TOTAL DUE PAYMENT-AS PER FINAL INVOICE US$]]/Tabela1[[#This Row],[PROFORMA (2026)]] -> 1.0116667 | L86: 22216.2 | M86: 22216.2 | N86: =Tabela1[[#This Row],[ADVANCE PAYMENT / FINAL PAYM''T/ NC (US$)]]-Tabela1[[#This Row],[TOTAL DUE PAYMENT-AS PER FINAL INVOICE US$]] -> 0 | O86: 114700.02 | P86: 64130 | Q86: paga | R86: abril'26 - notificado - SWIFT $22.216,20 (21 ABR 26) | S86: S
A87: 005.26 | B87: SUNLOCK SPA | C87: CHILE | D87: 9177 | E87: 46031 | F87: 46073 | G87: 30 days | H87: 30 | I87: =Tabela1[[#This Row],[DATA COLETA (ESTIMADA)]]+Tabela1[[#This Row],[days]] -> 46103 | J87: - | K87: - | N87: =Tabela1[[#This Row],[ADVANCE PAYMENT / FINAL PAYM''T/ NC (US$)]]-Tabela1[[#This Row],[TOTAL DUE PAYMENT-AS PER FINAL INVOICE US$]] -> 0 | O87: -- | P87: -- | Q87: parcial | R87: março'26- consolida 003.26 - ver acima
A88: 006.26 | B88: FLEX CHILE | C88: CHILE | D88: 9206 | E88: 46038 | F88: 46077 | G88: 90 Days | H88: 90 | I88: =Tabela1[[#This Row],[DATA COLETA (ESTIMADA)]]+Tabela1[[#This Row],[days]] -> 46167 | J88: =2250+1970 -> 4220 | K88: =Tabela1[[#This Row],[TOTAL DUE PAYMENT-AS PER FINAL INVOICE US$]]/Tabela1[[#This Row],[PROFORMA (2026)]] -> 0.87945024 | L88: 3711.28 | M88: 3711.25 | N88: =Tabela1[[#This Row],[ADVANCE PAYMENT / FINAL PAYM''T/ NC (US$)]]-Tabela1[[#This Row],[TOTAL DUE PAYMENT-AS PER FINAL INVOICE US$]] -> -0.03 | O88: 19160.97 | P88: 64173 | Q88: paga | R88: maio'26. 006.26 + 009.26 | SWIFT 28/05 ($ 3,711,25) - Dif -0,03
A89: 007.26 | B89: SUNLOCK SPA | C89: CHILE | D89: 9207 | E89: 46038 | F89: 46073 | G89: 30 days | H89: 30 | I89: =Tabela1[[#This Row],[DATA COLETA (ESTIMADA)]]+Tabela1[[#This Row],[days]] -> 46103 | J89: - | K89: - | N89: =Tabela1[[#This Row],[ADVANCE PAYMENT / FINAL PAYM''T/ NC (US$)]]-Tabela1[[#This Row],[TOTAL DUE PAYMENT-AS PER FINAL INVOICE US$]] -> 0 | O89: -- | P89: -- | Q89: parcial | R89: março'26- consolida 003.26 - ver acima
A90: 008.26 | B90: DIVINO | C90: URUGUAY | D90: 9233 | E90: 46048 | F90: 46078 | G90: 50% Pre Payment - 50% After Received | H90: 30 | I90: =Tabela1[[#This Row],[DATA COLETA (ESTIMADA)]]+Tabela1[[#This Row],[days]] -> 46108 | J90: 12080 | K90: =Tabela1[[#This Row],[TOTAL DUE PAYMENT-AS PER FINAL INVOICE US$]]/Tabela1[[#This Row],[PROFORMA (2026)]] -> 1.02525 | L90: 12385.02 | M90: =6040+6345.02 -> 12385.02 | N90: =Tabela1[[#This Row],[ADVANCE PAYMENT / FINAL PAYM''T/ NC (US$)]]-Tabela1[[#This Row],[TOTAL DUE PAYMENT-AS PER FINAL INVOICE US$]] -> 0 | O90: 63701.11 | P90: 64233 | Q90: paga | R90: março'26- Prepayment SWIFT 50% >$6.040 (28/01)/SWIFT final $6.345,02 (4/3)
A91: 009.26 | B91: FLEX CHILE | C91: CHILE | D91: 9246 | E91: 46052 | F91: 46077 | G91: 90 Days | H91: 90 | I91: =Tabela1[[#This Row],[DATA COLETA (ESTIMADA)]]+Tabela1[[#This Row],[days]] -> 46167 | K91: - | N91: =Tabela1[[#This Row],[ADVANCE PAYMENT / FINAL PAYM''T/ NC (US$)]]-Tabela1[[#This Row],[TOTAL DUE PAYMENT-AS PER FINAL INVOICE US$]] -> 0 | O91: -- | P91: -- | Q91: paga | R91: maio'26 - consolida 006.26 - ver acima | | SWIFT 28/05 ($ 3,711,25) - Dif -0,03
A92: 010.26 | B92: COLCHONES DEL PARAGUAY | C92: PARAGUAY | D92: 9469 | E92: 46066 | F92: 46077 | G92: Pre-payment | H92: 0 | I92: =Tabela1[[#This Row],[DATA COLETA (ESTIMADA)]]+Tabela1[[#This Row],[days]] -> 46077 | J92: 5496.5 | K92: =Tabela1[[#This Row],[TOTAL DUE PAYMENT-AS PER FINAL INVOICE US$]]/Tabela1[[#This Row],[PROFORMA (2026)]] -> 0.96752479 | L92: 5318 | M92: 5318 | N92: =Tabela1[[#This Row],[ADVANCE PAYMENT / FINAL PAYM''T/ NC (US$)]]-Tabela1[[#This Row],[TOTAL DUE PAYMENT-AS PER FINAL INVOICE US$]] -> 0 | O92: 27836 | P92: 64034 | Q92: paga | R92: Fevereiro'26-Inclui Frete ($815)- paga SWIFT 20/02
A93: 011.26 | B93: SUNLOCK SPA | C93: CHILE | D93: 9522 | E93: 46077 | F93: 46140 | G93: 30 days | H93: 90 | I93: =Tabela1[[#This Row],[DATA COLETA (ESTIMADA)]]+Tabela1[[#This Row],[days]] -> 46230 | J93: 19925 | K93: =Tabela1[[#This Row],[TOTAL DUE PAYMENT-AS PER FINAL INVOICE US$]]/Tabela1[[#This Row],[PROFORMA (2026)]] -> 1.2126806 | L93: =21016.12+3146.54 -> 24162.66 | M93: =8898.93+6575.25 -> 15474.18 | N93: =Tabela1[[#This Row],[ADVANCE PAYMENT / FINAL PAYM''T/ NC (US$)]]-Tabela1[[#This Row],[TOTAL DUE PAYMENT-AS PER FINAL INVOICE US$]] -> -8688.48 | O93: 118967.26 | P93: 65751 | Q93: parcial | R93: julho'26 -FINAL/ acuerdo pago 33% A vista/ 33% a 30 d / 33% a 60D|Incluye Frete| SWIFT 1($6575,25)filed04may.SWIFT 18sep $21.013,51
A94: 012.26 | B94: MULTIESPUMAS VISCARRA | C94: BOLIVIA | D94: 9534 | E94: 46078 | F94: 46119 | G94: Pre-payment | H94: 0 | I94: =Tabela1[[#This Row],[DATA COLETA (ESTIMADA)]]+Tabela1[[#This Row],[days]] -> 46119 | J94: 6500 | K94: =Tabela1[[#This Row],[TOTAL DUE PAYMENT-AS PER FINAL INVOICE US$]]/Tabela1[[#This Row],[PROFORMA (2026)]] -> 0.977 | L94: 6350.5 | M94: 6350.5 | N94: =Tabela1[[#This Row],[ADVANCE PAYMENT / FINAL PAYM''T/ NC (US$)]]-Tabela1[[#This Row],[TOTAL DUE PAYMENT-AS PER FINAL INVOICE US$]] -> 0 | O94: 33242.96 | P94: 65010 | Q94: paga | R94: março'26 - SWIFT 31/03 (6.350,50)
A95: 013.26 | B95: FLEX CHILE | C95: CHILE | D95: 9634 | E95: 46084 | F95: 46127 | G95: 90 Days | H95: 90 | I95: =Tabela1[[#This Row],[DATA COLETA (ESTIMADA)]]+Tabela1[[#This Row],[days]] -> 46217 | J95: 10258 | K95: =Tabela1[[#This Row],[TOTAL DUE PAYMENT-AS PER FINAL INVOICE US$]]/Tabela1[[#This Row],[PROFORMA (2026)]] -> 0.97019497 | L95: 9952.26 | M95: 9952.26 | N95: =Tabela1[[#This Row],[ADVANCE PAYMENT / FINAL PAYM''T/ NC (US$)]]-Tabela1[[#This Row],[TOTAL DUE PAYMENT-AS PER FINAL INVOICE US$]] -> 0 | O95: 49.600,08 | P95: 65456 | Q95: paga | R95: julho'26
A96: 014.26 | B96: SUPERSPUMA PARAGUAY (SAECA) | C96: PARAGUAY | D96: 9691 | E96: 46087 | F96: 46126 | G96: Pre Payment - 100% Counter Expedition | H96: 0 | I96: =Tabela1[[#This Row],[DATA COLETA (ESTIMADA)]]+Tabela1[[#This Row],[days]] -> 46126 | J96: 8189 | K96: =Tabela1[[#This Row],[TOTAL DUE PAYMENT-AS PER FINAL INVOICE US$]]/Tabela1[[#This Row],[PROFORMA (2026)]] -> 0.92085969 | L96: 7540.92 | M96: 7540.92 | N96: =Tabela1[[#This Row],[ADVANCE PAYMENT / FINAL PAYM''T/ NC (US$)]]-Tabela1[[#This Row],[TOTAL DUE PAYMENT-AS PER FINAL INVOICE US$]] -> 0 | O96: 39474.47 | P96: 65022 | Q96: paga | R96: abril'26 - SWIFT 17/04-recibido 21/04
A97: 015.26 | B97: BED TIME | C97: ARGENTINA | D97: 9695 | E97: 46091 | F97: 46133 | G97: 60 days, after customs clearance | H97: 70 | I97: =Tabela1[[#This Row],[DATA COLETA (ESTIMADA)]]+Tabela1[[#This Row],[days]] -> 46203 | J97: 48160 | K97: =Tabela1[[#This Row],[TOTAL DUE PAYMENT-AS PER FINAL INVOICE US$]]/Tabela1[[#This Row],[PROFORMA (2026)]] -> 1.1275596 | L97: 54303.27 | M97: 54303.27 | N97: =Tabela1[[#This Row],[ADVANCE PAYMENT / FINAL PAYM''T/ NC (US$)]]-Tabela1[[#This Row],[TOTAL DUE PAYMENT-AS PER FINAL INVOICE US$]] -> 0 | O97: =240761.17+30760.62 -> 271521.79 | P97: 65382/65383 | Q97: paga | R97: junho'26 - 2da NF por los 2K mts extra producidos/invoice única||SWIFT 21/07 $54303,27 | S97: N
A98: 016.26 | B98: DIST. CASEROS | C98: ARGENTINA | D98: 9942 | E98: 46118 | F98: 46156 | G98: 30 days | H98: 30 | I98: =Tabela1[[#This Row],[DATA COLETA (ESTIMADA)]]+Tabela1[[#This Row],[days]] -> 46186 | J98: 15370 | K98: =Tabela1[[#This Row],[TOTAL DUE PAYMENT-AS PER FINAL INVOICE US$]]/Tabela1[[#This Row],[PROFORMA (2026)]] -> 1.2234268 | L98: =16122.07+2682 -> 18804.07 | M98: 18804.07 | N98: =Tabela1[[#This Row],[ADVANCE PAYMENT / FINAL PAYM''T/ NC (US$)]]-Tabela1[[#This Row],[TOTAL DUE PAYMENT-AS PER FINAL INVOICE US$]] -> 0 | O98: 94595.71 | P98: 66068 | Q98: paga | R98: junho'26 / Incluye frete ($2.682)-SWIFT (02/07) $18.804,07 | S98: on going
A99: 017.26 | B99: POLYMAX EL GALO | C99: URUGUAY | D99: 9747 | E99: 46094 | F99: 46148 | G99: 60 days | H99: 60 | I99: =Tabela1[[#This Row],[DATA COLETA (ESTIMADA)]]+Tabela1[[#This Row],[days]] -> 46208 | J99: =8500+13158 -> 21658 | K99: =Tabela1[[#This Row],[TOTAL DUE PAYMENT-AS PER FINAL INVOICE US$]]/Tabela1[[#This Row],[PROFORMA (2026)]] -> 1.0088882 | L99: =21850.5 -> 21850.5 | M99: =6000+8000+8000-0.73 -> 21999.27 | N99: =Tabela1[[#This Row],[ADVANCE PAYMENT / FINAL PAYM''T/ NC (US$)]]-Tabela1[[#This Row],[TOTAL DUE PAYMENT-AS PER FINAL INVOICE US$]] -> 148.77 | O99: 108972.81 | P99: 65581 | Q99: paga | R99: julho'26- consolida com 017 + 021.26 - revisar esquema de pgos/muestras $297| SWIFT 17/07 $6.000| SWIFT 10/09 $8000+SWIFT 28/09 $8.000
A100: 018.26 | B100: FLEX CHILE | C100: CHILE | D100: 9771 | E100: 46099 | F100: 46146 | G100: 90 Days | H100: 90 | I100: =Tabela1[[#This Row],[DATA COLETA (ESTIMADA)]]+Tabela1[[#This Row],[days]] -> 46236 | J100: 8168 | K100: =Tabela1[[#This Row],[TOTAL DUE PAYMENT-AS PER FINAL INVOICE US$]]/Tabela1[[#This Row],[PROFORMA (2026)]] -> 1.0710247 | L100: 8748.13 | M100: 8748.13 | N100: =Tabela1[[#This Row],[ADVANCE PAYMENT / FINAL PAYM''T/ NC (US$)]]-Tabela1[[#This Row],[TOTAL DUE PAYMENT-AS PER FINAL INVOICE US$]] -> 0 | O100: 44066.08 | P100: 66014 | Q100: paga | R100: agosto'26 - SWIFT 13/08 ($8748,13)
...

Sheet BASE DADOS CONTATOS
A1: CONEXÃO MALHAS - CONTATOS CLAVES / CLIENTES ATIVOS
A3: Regiao | B3: Sub-regiao | C3: Clientes | D3: Ativos | E3: Inativos | F3: Prospect | G3: Potencial | H3: Estrategicos | I3: Sensiveis | J3: contato | K3: cargo | L3: email | M3: telefone | N3: Observ.
A4: Chile | B4: Santiago | C4: Flex Equipos de Descanso | D4: Sim | E4: - | F4: - | G4: Grande | H4: Sim | I4: Sim | J4: Paulina Mena | K4: Compras | L4: paulina.mena@flex.es | M4: 56 96205 0626 | N4: amostras/ desenvolvimento/OC
A5: Chile | B5: Santiago | C5: Flex Equipos de Descanso | D5: Sim | G5: Grande | H5: Sim | I5: Sim | J5: Danae Briones | K5: Importações | L5: danae.briones@flex.es | M5: +56 9 5514 2584
A6: Chile | B6: Santiago | C6: Flex Equipos de Descanso | D6: Sim | G6: Grande | H6: Sim | I6: Sim | J6: Francesca Seitz | K6: Marketing | L6: francesca.seitz@flex.es | M6: +56 9 3451 9331
A7: Chile | B7: Santiago | C7: Flex Equipos de Descanso | D7: Sim | G7: Grande | H7: Sim | I7: Sim | J7: Angelo Almonacid | K7: Supply | L7: angelo.almonacid@flex.es | M7: +56 9 4400 6214 | N7: Manager of others
A8: Chile | B8: Santiago | C8: Sunlock (Serta) | D8: Sim | E8: - | F8: - | G8: Pequeno | H8: - | I8: - | J8: Juan Carlos Villarroel | K8: Compras | L8: jcvillarroel@sunlock.cl | M8: (+56) 98529-7739
A9: Chile | B9: Santiago | C9: Sunlock (Serta) | D9: Sim | G9: Pequeno | H9: - | I9: - | J9: Felipe San Martin | K9: Socio | L9: fsanmartin@multimetal.cl | M9: +56 9 9939 1194 | N9: Estrategico/ pagamentos
A10: Chile | B10: Santiago | C10: Muebles MPR | D10: Sim | E10: - | F10: - | G10: Pequeno | H10: - | I10: - | J10: Misael | K10: Financeiro | L10: NA | M10: +56 9 5413 0257
A11: Chile | B11: Santiago | C11: Muebles MPR | D11: Sim | G11: Pequeno | H11: - | I11: - | J11: Daniel Carvajal | K11: Socio | L11: mpr.muebleria@gmail.com | M11: +56 9 7977 0882
A12: Paraguai | B12: Asuncao | C12: SuperSpuma | D12: Sim | E12: - | F12: - | G12: Medio | H12: - | I12: - | J12: Leticia Roig | K12: Compras | L12: leticia.roig@superspuma.com.py | M12: +595 985 629024
A13: Paraguai | B13: Asuncao | C13: SuperSpuma | D13: Sim | E13: - | F13: - | G13: Medio | H13: - | I13: - | J13: Maria Laura | K13: Marketing | L13: maria.laura@superspuma.com.py | M13: +595 986 154856
A14: Paraguai | B14: Asuncao | C14: SuperSpuma | D14: Sim | E14: - | F14: - | G14: Medio | H14: - | I14: - | J14: Ruth Sosa | K14: Importações | L14: ruth.sosa@superspuma.com.py | M14: +595 971 889820
A15: Paraguai | B15: Asuncao | C15: Inmapol (Industria de la madera) | D15: Sim | E15: - | F15: - | G15: Pequeno | H15: - | I15: - | J15: Marcos | K15: Socio | L15: madrisa@inmapol.com.py | M15: 595 21 942 599
A16: Paraguai | B16: Asuncao | C16: Inmapol (Industria de la madera) | D16: Sim | E16: - | F16: - | G16: Pequeno | H16: - | I16: - | J16: Alejandro Abraham | K16: Representante | L16: ale@erwinabraham.com | M16: NA | N16: intermediario
A17: Paraguai | B17: Luque | C17: Materassi (Sea Trading) | D17: Sim | E17: - | F17: - | G17: Pequeno | H17: - | I17: - | J17: Alcibiades Greco | K17: Socio | L17: unicornio_py@yahoo.es | M17: 595 982 119084
A18: Paraguai | B18: Luque | C18: Materassi (Sea Trading) | D18: Sim | E18: - | F18: - | G18: Pequeno | H18: - | I18: - | J18: Yessica | K18: Compras | L18: Yessicanuf@gmail.com | M18: NA
A19: Paraguai | B19: Santa Rita | C19: Nature (NM Espuma) | D19: Sim | E19: - | F19: - | G19: Pequeno | H19: - | I19: - | J19: Federico Nuñez | K19: Financeiro | L19: federico@nunez.com.py | M19: +595 983 603791
A20: Paraguai | B20: Santa Rita | C20: Nature (NM Espuma) | D20: Sim | E20: - | F20: - | G20: Pequeno | H20: - | I20: - | J20: Jorge Nuñez | K20: Socio | L20: jorge@nunez.com.py | M20: +595 983 688644
A21: Paraguai | B21: Santa Rita | C21: Nature (NM Espuma) | D21: Sim | E21: - | F21: - | G21: Pequeno | H21: - | I21: - | J21: Susana Diaz | K21: Compras | L21: administracion@nature.com.py | M21: +595 982 795064 | N21: admin
A22: Argentina | B22: Buenos Aires | C22: Simmons Argentina | D22: Sim | E22: - | F22: - | G22: Grande | H22: Sim | I22: Sim | J22: Martin Miller | K22: Representante | L22: comercial@martinmiller.com.ar | M22: +54 9 11 6237-7072 | N22: intermediario
A23: Uruguai | B23: Montevideo | C23: Divino | D23: Sim | E23: - | F23: - | G23: Grande | H23: Sim | I23: Sim | J23: FRANCO MACHAO | K23: Comex | L23: franco.machao@divino.com.uy | M23: + 598 (2) 506.1262
A24: Uruguai | B24: Montevideo | C24: Divino | D24: Sim | E24: - | F24: - | G24: Grande | H24: Sim | I24: Sim | J24: Agustina Vuco | K24: Comex | L24: agustina.vuco@divino.com.uy | M24: +598 98 456 659
A25: Uruguai | B25: Montevideo | C25: Divino | D25: Sim | E25: - | F25: - | G25: Grande | H25: Sim | I25: Sim | J25: Emilia Torres | K25: Comex | L25: emilia.torres@divino.com.uy | M25: +598 98 455 154 | N25: comex@divino.com.uy
A26: Uruguai | B26: Montevideo | C26: Divino | D26: Sim | E26: - | F26: - | G26: Grande | H26: Sim | I26: Sim | J26: Esteban Saibene | K26: Compras | L26: esteban.saibene@divino.com.uy | M26: +598 92 873 272 | N26: Moveis
A27: Uruguai | B27: Montevideo | C27: Divino | D27: Sim | E27: - | F27: - | G27: Grande | H27: Sim | I27: Sim | J27: Federico Durán | K27: Operações | L27: federico.duran@divino.com.uy | M27: +598 99 919 936 | N27: Gte Gral Fabrica
A28: Uruguai | B28: Montevideo | C28: Divino | D28: Sim | E28: - | F28: - | G28: Grande | H28: Sim | I28: Sim | J28: Fernando Rugiero | K28: Compras | L28: fernando.rugiero@divino.com.uy | M28: +598 92 622 679 | N28: Tecido
A29: Uruguai | B29: Montevideo | C29: Divino | D29: Sim | E29: - | F29: - | G29: Grande | H29: Sim | I29: Sim | J29: Francisco Studer | K29: Comex | L29: francisco.studer@divino.com.uy | M29: +598 92 815 133 | N29: Manager of others
A30: Uruguai | B30: Montevideo | C30: Divino | D30: Sim | E30: - | F30: - | G30: Grande | H30: Sim | I30: Sim | J30: Hernán Berro | K30: Supply | L30: hernan.berro@divino.com.uy | M30: +598 98 988 226 | N30: Director
A31: Uruguai | B31: Montevideo | C31: Divino | D31: Sim | E31: - | F31: - | G31: Grande | H31: Sim | I31: Sim | J31: Cecilia Solodilin | K31: Compras | L31: cecilia.solodilin@divino.com.uy | M31: +59825061262 | N31: Asistente de Fernando Rugiero
A32: Uruguai | B32: Montevideo | C32: Polymax | D32: Sim | E32: - | F32: - | G32: Medio | H32: Sim | I32: Sim | J32: Gonzalo Rodriguez | K32: Gerente Gral | L32: grodriguez@polymax.com.uy | M32: +598 2320 2320
A33: Uruguai | B33: Montevideo | C33: Polymax | D33: Sim | E33: - | F33: - | G33: Medio | H33: Sim | I33: Sim | J33: Eliana Garyalde | K33: Asistente Gerencia | L33: asistente.gerencia@polymax.com.uy | M33: +598 94 507 590
A34: Equador | B34: Guayaquil | C34: Productos Paraiso do Ecuador | D34: Sim | E34: - | F34: - | G34: Grande | H34: Sim | I34: - | J34: Diego Perez | K34: Operações | L34: diegoperez@paraiso.com.ec | M34: +593 98 728 8947 | N34: Gte Gral Fabrica
A35: Equador | B35: Guayaquil | C35: Productos Paraiso do Ecuador | D35: Sim | E35: - | F35: - | G35: Grande | H35: Sim | I35: - | J35: Francisco Rivas | K35: Marketing | L35: gerencia.c@paraiso.com.ec | M35: +593 99 440 2827
A36: Equador | B36: Guayaquil | C36: Productos Paraiso do Ecuador | D36: Sim | E36: - | F36: - | G36: Grande | H36: Sim | I36: - | J36: Jose Luis Andrango | K36: Compras | L36: joseandrango@paraiso.com.ec | M36: +593 99 161 0288
A37: Equador | B37: Guayaquil | C37: Productos Paraiso do Ecuador | D37: Sim | E37: - | F37: - | G37: Grande | H37: Sim | I37: - | J37: Joana Ñato | K37: Financeiro | L37: comexuio@paraiso.com.ec | M37: +593 99 784 7907 | N37: pagamento
A38: Equador | B38: Guayaquil | C38: Productos Paraiso do Ecuador | D38: Sim | E38: - | F38: - | G38: Grande | H38: Sim | I38: - | J38: Maria José Camacho | K38: Comex | L38: comexgye@paraiso.com.ec | M38: +593 99 949 4115
A39: Equador | B39: Guayaquil | C39: Productos Paraiso do Ecuador | D39: Sim | E39: - | F39: - | G39: Grande | H39: Sim | I39: - | J39: René Cortes | K39: Gerente Gral | L39: gerenciagye@paraiso.com.ec | M39: +593 99 377 7690 | N39: pagamento
A40: Equador | B40: Cuenca | C40: Colineal | D40: Sim | E40: - | F40: - | G40: Medio | H40: - | I40: - | J40: Gabriela Briones | K40: Marketing | L40: gabrielabriones@colinealcorp.com | M40: +593 99 530 6517
A41: Equador | B41: Cuenca | C41: Colineal | D41: Sim | E41: - | F41: - | G41: Medio | H41: - | I41: - | J41: Patricio Culquer | K41: Compras | L41: patricioculquer@colinealcorp.com | M41: +593 99 847 9284
A42: Equador | B42: Cuenca | C42: Colineal | D42: Sim | E42: - | F42: - | G42: Medio | H42: - | I42: - | J42: Patricia Arce | K42: Comex | L42: importaciones@colinealcorp.com | M42: +593 99 151 9067
A43: Bolivia | B43: Santa Cruz | C43: Maxi King | D43: Sim | E43: - | F43: - | G43: Grande | H43: - | I43: - | J43: Claudia Siles | K43: Comex | L43: importaciones@maxiking.com.bo | M43: +591 75002325 | N43: pagamento
A44: Bolivia | B44: Santa Cruz | C44: Maxi King | D44: Sim | E44: - | F44: - | G44: Grande | H44: - | I44: - | J44: Livio Zozzoli | K44: Socio | L44: liviozozzoli@maxiking.com.bo | M44: +591 76640034
A45: Bolivia | B45: Santa Cruz | C45: Maxi King | D45: Sim | E45: - | F45: - | G45: Grande | H45: - | I45: - | J45: Silvia Zerda | K45: Socio | L45: silviazerda@maxiking.com.bo | M45: +591 76640036
A46: Bolivia | B46: Santa Cruz | C46: Heaven (David Moreno) | D46: Sim | E46: - | F46: - | G46: Pequeno | H46: - | I46: - | J46: Severiano Melgar | K46: Financeiro | L46: jefecompras@colchonesheaven.com | M46: +591 78516162
A47: Bolivia | B47: Santa Cruz | C47: Heaven (David Moreno) | D47: Sim | E47: - | F47: - | G47: Pequeno | H47: - | I47: - | J47: David Moreno | K47: Socio | L47: david_moreno_2000@yahoo.com | M47: +591 70871171 | N47: compras@colchonesheaven.com
A48: Bolivia | B48: Santa Cruz | C48: Heaven (David Moreno) | D48: Sim | E48: - | F48: - | G48: Pequeno | H48: - | I48: - | J48: Daniel Garnica | K48: Compras | L48: NA | M48: +591 75501534
A49: Bolivia | B49: Santa Cruz | C49: Heaven (David Moreno) | D49: Sim | E49: - | F49: - | G49: Pequeno | H49: - | I49: - | J49: Siro | K49: Compras | L49: siro22091975@gmail.com | M49: +591 67898756
A50: Bolivia | B50: Santa Cruz | C50: Wenturs Trade (Distribuidor) | D50: Sim | E50: - | F50: - | G50: Pequeno | H50: - | I50: - | J50: Sr. Josimar Kronembold | K50: Socio | L50: NA | M50: +591 75381793
A51: Bolivia | B51: Santa Cruz | C51: Wenturs Trade (Distribuidor) | D51: Sim | E51: - | F51: - | G51: Pequeno | H51: - | I51: - | J51: Arnaldo | K51: Socio | L51: NA | M51: +591 69050221
A52: Venezuela | B52: Valencia | C52: Corporacion CLC (Colchones CLC) | D52: Sim | E52: - | F52: - | G52: Grande | H52: - | I52: - | J52: Jasmin Dugga | K52: Compras | L52: NA | M52: +58 412-8317925
A53: Colombia | B53: Medellin | C53: Comodissimo (Espumas Plasticas) | D53: Sim | E53: - | F53: - | G53: Grande | H53: Sim | I53: - | J53: Manuela Torres | K53: Compras | L53: NA | M53: +57 311 7282925
A54: Colombia | B54: Medellin | C54: Comodissimo (Espumas Plasticas) | D54: Sim | E54: - | F54: - | G54: Grande | H54: Sim | I54: - | J54: Veronica Ardila | K54: Marketing | L54: NA | M54: +57 300 2422425
A55: Guatemala | B55: Guatemala | C55: Facenco | D55: Sim | E55: - | F55: - | G55: Grande | H55: Sim | I55: Sim | J55: Nestor Alvarado | K55: Compras | L55: NA | M55: +502 5191 1018
A56: Guatemala | B56: Guatemala | C56: Facenco | D56: Sim | E56: - | F56: - | G56: Grande | H56: Sim | I56: Sim | J56: Mishell Fernandez | K56: Marketing | L56: NA | M56: +502 5525 8000
A57: Guatemala | B57: Guatemala | C57: Facenco | D57: Sim | E57: - | F57: - | G57: Grande | H57: Sim | I57: Sim | J57: Rudy | K57: Vendas | L57: NA | M57: +502 5702 8641 | N57: Dir. Comercial / Socio
A58: Guatemala | B58: Guatemala | C58: Industria Ultra | D58: Sim | E58: - | F58: - | G58: Medio | H58: - | I58: - | J58: Juan Solares | K58: Socio | L58: NA | M58: +502 5306 1895
A59: Guatemala | B59: Guatemala | C59: Industria Ultra | D59: Sim | E59: - | F59: - | G59: Medio | H59: - | I59: - | J59: Luis Pedro Solares | K59: Socio | L59: NA | M59: +502 5204 8138
A60: Guatemala | B60: Guatemala | C60: Camas Florida | D60: Sim | E60: - | F60: - | G60: Grande | H60: - | I60: - | J60: Annie | K60: NA | L60: NA | M60: +504 3151-3705
A61: Guatemala | B61: Guatemala | C61: Camas Florida | D61: Sim | E61: - | F61: - | G61: Grande | H61: - | I61: - | J61: Jacqueline | K61: NA | L61: NA | M61: +502 4570 7194
A62: Honduras | B62: Tegucigalpa | C62: Proahfoam | D62: Sim | E62: - | F62: - | G62: Medio | H62: - | I62: - | J62: Arturo | K62: NA | L62: NA | M62: +504 9990-8010
A63: Honduras | B63: Tegucigalpa | C63: Proahfoam | D63: Sim | E63: - | F63: - | G63: Medio | H63: - | I63: - | J63: Mariela Aguilar | K63: NA | L63: NA | M63: +504 9443-2161
A64: Honduras | B64: Tegucigalpa | C64: Camas Florida | D64: Sim | E64: - | F64: - | G64: Medio | H64: - | I64: - | J64: Claudia Acosta | K64: NA | L64: NA | M64: +504 3157-3432
A65: Cuba | B65: Mariel | C65: Sueños Tropicales (AGT) | D65: Sim | E65: - | F65: - | G65: Grande | H65: - | I65: - | J65: Neorquides | K65: NA | L65: NA | M65: +34 641 91 60 94 | N65: Komfort Cuba
A66: Cuba | B66: Mariel | C66: Sueños Tropicales (AGT) | D66: Sim | E66: - | F66: - | G66: Grande | H66: - | I66: - | J66: Ricardo | K66: NA | L66: NA | M66: +53 5 2639277
A67: Cuba | B67: Mariel | C67: Sueños Tropicales (AGT) | D67: Sim | E67: - | F67: - | G67: Grande | H67: - | I67: - | J67: Walter Castro | K67: NA | L67: NA | M67: +1 (809) 224-3758

Sheet SUMMARY
A1: FLUXO DE CREDITO | S1: PENDING VALUES | AK1: DEADLINES - DATA - VALUE
S2: Anos | T2: (Todas) | AK2: STATUS PGTO | AL2: (Varios elementos)
A3: Suma de TOTAL DUE BALANCE (US$) | B3: STATUS | S3: STATUS PGTO | T3: (Varios elementos)
A4: CLIENTES | B4: cancelar | C4: Devolução | D4: futura | E4: Não procede | F4: paga | G4: parcial | H4: pendente | I4: NC | J4: on hold | K4: Total general (DUE) | AL4: STATUS
A5: BED TIME | D5: -83980 | F5: 0 | K5: -83980 | S5: Suma de TOTAL DUE BALANCE (US$) | T5: mês | AL5: Suma de DATA VENCIMENTO/ | AN5: Suma de TOTAL DUE BALANCE (US$) | AP5: Total Suma de DATA VENCIMENTO/ | AQ5: Total Suma de TOTAL DUE BALANCE (US$)
A6: COLCHONES DEL PARAGUAY | D6: -3685 | F6: 0 | K6: -3685 | S6: CLIENTES | T6: ene | U6: mar | V6: jul | W6: ago | X6: sep | Y6: oct | Z6: nov | AA6: dic | AB6: Total general | AL6: 2025 | AM6: 2026 | AN6: 2025 | AO6: 2026
A7: CUBA - David Rosabal Container 1 | G7: -13118.19 | K7: -13118.19 | S7: CUBA - David Rosabal Container 1 | V7: -13118.19 | AB7: -13118.19 | AK7: CLIENTES
A8: CUBA - David Rosabal Container 2 | G8: 0 | K8: 0 | S8: CUBA - David Rosabal Container 2 | V8: 0 | AB8: 0 | AK8: CUBA - David Rosabal Container 1 | AL8: 45860 | AN8: -13118.19 | AP8: 45860 | AQ8: -13118.19
A9: DAVID MORENO VISCARRA | F9: 0 | K9: 0 | S9: FRAZADAS ARTESANALES (LA GRANDE) | T9: -144.995 | AB9: -144.995 | AK9: CUBA - David Rosabal Container 2 | AL9: 45860 | AN9: 0 | AP9: 45860 | AQ9: 0
A10: DIST. CASEROS | F10: 205.33 | K10: 205.33 | S10: SUNLOCK SPA | U10: 8898.93 | V10: -8688.48 | AA10: -16234.12 | AB10: -16023.67 | AK10: FRAZADAS ARTESANALES (LA GRANDE) | AM10: 46028 | AO10: -144.995 | AP10: 46028 | AQ10: -144.995
A11: DIVINO | B11: 0 | F11: 0 | K11: 0 | S11: YP S.A. (Grupo Suenolar) | X11: -37 | AB11: -37 | AK11: SUNLOCK SPA | AM11: 230922 | AO11: -16023.67 | AP11: 230922 | AQ11: -16023.67
A12: FLEX CHILE | B12: 0 | C12: 0 | D12: -24285.93 | E12: 0 | F12: -0.03 | K12: -24285.96 | S12: TEC NIPONA PERÚ (AMAZHEL) | W12: -229.32 | AB12: -229.32 | AK12: YP S.A. (Grupo Suenolar) | AM12: 46268 | AO12: -37 | AP12: 46268 | AQ12: -37
A13: FRAZADAS ARTESANALES (LA GRANDE) | F13: 0 | G13: -144.995 | K13: -144.995 | S13: PARAISO DEL ECUADOR | V13: -8166.7 | Y13: -35 | Z13: -44.12 | AB13: -8245.82 | AK13: TEC NIPONA PERÚ (AMAZHEL) | AM13: 46245 | AO13: -229.32 | AP13: 46245 | AQ13: -229.32
A14: IMPORTADORA TERRA (MOVELPRO SRL) | F14: 514.7 | K14: 514.7 | S14: Total general | T14: -144.995 | U14: 8898.93 | V14: -29973.37 | W14: -229.32 | X14: -37 | Y14: -35 | Z14: -44.12 | AA14: -16234.12 | AB14: -37798.995 | AK14: PARAISO DEL ECUADOR | AL14: 91936 | AM14: 46224 | AN14: -79.12 | AO14: -8166.7 | AP14: 138160 | AQ14: -8245.82
A15: INDUCOL | F15: -0.01 | K15: -0.01 | AK15: Total general (DUE) | AL15: 183656 | AM15: 415687 | AN15: -13197.31 | AO15: -24601.685 | AP15: 599343 | AQ15: -37798.995
A16: INMAPOL | F16: 0 | K16: 0
A17: LAMITEX S.A. | F17: 0 | K17: 0
A18: MAXI KING | F18: 0 | K18: 0
A19: MULTIESPUMAS VISCARRA | D19: -12400.4 | F19: 0 | K19: -12400.4
A20: SEA TRADING (MATERASSI) | F20: 0 | K20: 0
A21: SERVAN EXPORTADORA DE MANUFACTURADOS LTDA (ABBA) | F21: 0 | K21: 0
A22: SIMMONS ARGENTINA | F22: 0 | K22: 0
A23: SPRINGWALL - VAZQUEZ SACII | F23: 0 | K23: 0
A24: SUNLOCK | F24: 0 | K24: 0
A25: SUNLOCK SPA | F25: 18642.4 | G25: 210.45 | H25: -16234.12 | K25: 2618.73
A26: SUPERSPUMA PARAGUAY (SAECA) | F26: 0 | K26: 0
A27: YP S.A. (Grupo Suenolar) | F27: 0 | G27: -37 | K27: -37
A28: LIMANSKY S.S. | D28: -79126.937 | F28: 0 | I28: -735.68 | K28: -79862.617
A29: TEXTIL FIBREX | F29: -79 | K29: -79
A30: POLYMAX EL GALO | D30: -19888.12 | F30: 256.77 | K30: -19631.35
A31: INDUSTRIAL REGAL | F31: 0 | K31: 0
A32: AGT - AMERICAN GARMENT | J32: -67760 | K32: -67760
A33: TEC NIPONA PERÚ (AMAZHEL) | G33: -229.32 | K33: -229.32
A34: COLOR LIVING | D34: -65775.51 | K34: -65775.51
A35: MANTAHUE SPA | F35: 0 | K35: 0
A36: ATLAS EAS | F36: 0 | K36: 0
A37: PARAISO DEL ECUADOR | B37: 0 | F37: 694.8 | G37: -79.12 | H37: -8166.7 | K37: -7551.02
A38: COLCHONES ESPUMIX (GOVER SPA) | G38: -24444.88 | K38: -24444.88
A39: YP S.A. (SUEÑOLAR) | D39: -9600 | K39: -9600
A40: Total general (DUE) | B40: 0 | C40: 0 | D40: -298741.9 | E40: 0 | F40: 20234.96 | G40: -37843.055 | H40: -24400.82 | I40: -735.68 | J40: -67760 | K40: -409246.49

Sheet INMAPOL

Sheet notificação clientes
B1: GESTÃO DE PAGAMENTO | D1: =TODAY() -> 46296 | I1: revisar abril- fim do mês
B3: INVOICE | C3: CUSTOMER | D3: TOTAL VALUE INVOICE US$ | E3: ADVANCE PAYMENT /CREDIT NOTE US$ | F3: TOTAL DUE BALANCE US$ | G3: DUE MONTH | H3: STATUS | I3: NOTIFICATION DATE/ EMAILs | J3: OBSERV.
B4: 221.25 | C4: LAMITEX S.A. | D4: 25047.07 | E4: =23905+1142.07 -> 25047.07 | F4: =Tabela13[[#This Row],[TOTAL VALUE INVOICE US$]]-Tabela13[[#This Row],[ADVANCE PAYMENT /CREDIT NOTE US$]] -> 0 | G4: PAGA | H4: PAGA | I4: 46076 | J4: Pending - Notificado- SWIFT 24/02 ($23905) - Saldo pendiente
B5: 220.25 | C5: SUNLOCK SPA | D5: =15772.24+346.92 -> 16119.16 | E5: =4929.86+5597.15+5592.15 -> 16119.16 | F5: =Tabela13[[#This Row],[TOTAL VALUE INVOICE US$]]-Tabela13[[#This Row],[ADVANCE PAYMENT /CREDIT NOTE US$]] -> 0 | G5: JAN/26 | H5: PAGA | I5: 04/02/2026 - Abril - consolidado 06/04 (WA CR) | J5: Pending - Notificado (consolidado)
B6: 217.25 | C6: FLEX CHILE | D6: 6482.4 | F6: =Tabela13[[#This Row],[TOTAL VALUE INVOICE US$]]-Tabela13[[#This Row],[ADVANCE PAYMENT /CREDIT NOTE US$]] -> 6482.4 | G6: PAGA | H6: PAGA | I6: 46121 | J6: pending - notificado
B7: 216.25 | C7: DIVINO | D7: 20124.81 | E7: =11502.5+8622.31 -> 20124.81 | F7: =Tabela13[[#This Row],[TOTAL VALUE INVOICE US$]]-Tabela13[[#This Row],[ADVANCE PAYMENT /CREDIT NOTE US$]] -> 0 | G7: PAGA | H7: PAGA | J7: Fechamento jan26
B8: 215.25 | C8: POLYMAX | D8: 13678.46 | E8: =3633.73+10044 -> 13677.73 | F8: =Tabela13[[#This Row],[TOTAL VALUE INVOICE US$]]-Tabela13[[#This Row],[ADVANCE PAYMENT /CREDIT NOTE US$]] -> 0.73 | G8: FEB/26 | H8: PAGA | I8: 03/03/2026 - Abril - consolidado 06/04 (WA CR)/1004 | J8: Ver esquema de pgos
B9: 212.25 | C9: FRAZADAS ARTESANALES (LA GRANDE) | D9: 44228.245 | E9: 44083.25 | F9: =Tabela13[[#This Row],[TOTAL VALUE INVOICE US$]]-Tabela13[[#This Row],[ADVANCE PAYMENT /CREDIT NOTE US$]] -> 144.995 | G9: JAN/26 | H9: PARCIAL | I9: 25/02/2026 -nunca respondeu sobre saldo pendiente | J9: Pending - swift final 22/12/25 - valor inferior notificado (25/02)
B10: 211.25 | C10: SUPERSPUMA PARAGUAY (SAECA) | D10: 6552 | F10: =Tabela13[[#This Row],[TOTAL VALUE INVOICE US$]]-Tabela13[[#This Row],[ADVANCE PAYMENT /CREDIT NOTE US$]] -> 6552 | G10: PAGA | H10: PAGA | J10: F-UP Faturamento
B11: 211.25 | C11: SUPERSPUMA | D11: 19504.93 | E11: 19504.93 | F11: =Tabela13[[#This Row],[TOTAL VALUE INVOICE US$]]-Tabela13[[#This Row],[ADVANCE PAYMENT /CREDIT NOTE US$]] -> 0 | G11: PAGA | H11: PAGA | J11: Notificar antes de férias coletivas
B12: 210.25 | C12: SUNLOCK SPA | D12: 13908.91 | E12: ='GESTAO CREDITO E PAGAMENTOS'!M70 -> 18900.77 | F12: =Tabela13[[#This Row],[TOTAL VALUE INVOICE US$]]-Tabela13[[#This Row],[ADVANCE PAYMENT /CREDIT NOTE US$]] -> -4991.86 | G12: PAGA | H12: PAGA | I12: 15/01 - 04/02 | J12: PAGO Pending - Notificado (consolida 209 + 210.25)- PARTE PGO SWIFT 23/03- saldo pendiente- Pago 24/04
B13: 208.25 | C13: FLEX CHILE | D13: 4288.53 | F13: =Tabela13[[#This Row],[TOTAL VALUE INVOICE US$]]-Tabela13[[#This Row],[ADVANCE PAYMENT /CREDIT NOTE US$]] -> 4288.53 | G13: PAGA | H13: PAGA
B14: 206.25 | C14: FLEX CHILE | D14: 2826 | E14: 2826 | F14: =Tabela13[[#This Row],[TOTAL VALUE INVOICE US$]]-Tabela13[[#This Row],[ADVANCE PAYMENT /CREDIT NOTE US$]] -> 0 | G14: PAGA | H14: PAGA | J14: Fechamento jan26
B15: 205.25 | C15: PARAÍSO DEL ECUADOR | D15: 738.92 | E15: 694.8 | F15: =Tabela13[[#This Row],[TOTAL VALUE INVOICE US$]]-Tabela13[[#This Row],[ADVANCE PAYMENT /CREDIT NOTE US$]] -> 44.12 | G15: PAGA | H15: PAGA | I15: 13/11/2025 - 24/11 - 26/11 | J15: Notificado - pending - 192.25 + saldo 205.25 ($42,12)
B16: 204.25 | C16: COLCHONES PRINCE | D16: =6554.95 -> 6554.95 | E16: 2000 | F16: =Tabela13[[#This Row],[TOTAL VALUE INVOICE US$]]-Tabela13[[#This Row],[ADVANCE PAYMENT /CREDIT NOTE US$]] -> 4554.95 | G16: PAGA | H16: PAGA | I16: 45987 | J16: Notificado - invoices consolidadas 204.25 +219.25
B17: 201.25 | C17: SERVAN EXPORTADORA DE MANUFACTURADOS LTDA (ABBA) | D17: 29893.05 | E17: 5310 | F17: =Tabela13[[#This Row],[TOTAL VALUE INVOICE US$]]-Tabela13[[#This Row],[ADVANCE PAYMENT /CREDIT NOTE US$]] -> 24583.05 | G17: finalizado | H17: PAGA | I17: Feito boleto Vence 20/11 | J17: Notificar com fechamento Outubro-Faturamento em R$ - inclui frete (R$2.483,07 / Dif vs cotado)
B18: 200.25 | C18: MULTIESPUMAS VISCARRA | D18: 16624.3 | E18: 16624.3 | F18: =Tabela13[[#This Row],[TOTAL VALUE INVOICE US$]]-Tabela13[[#This Row],[ADVANCE PAYMENT /CREDIT NOTE US$]] -> 0 | G18: PAGA | H18: PAGA | I18: 13/11/2025 - 24/11 - 10/12 | J18: Pending - Notificado
B19: 199.25 | C19: SUPERSPUMA PARAGUAY SAECA | D19: 14004.62 | E19: 0 | F19: =Tabela13[[#This Row],[TOTAL VALUE INVOICE US$]]-Tabela13[[#This Row],[ADVANCE PAYMENT /CREDIT NOTE US$]] -> 14004.62 | G19: PAGA | H19: PAGA | I19: 45974 | J19: Pago 02/10/25 - Copia Swift enviada pelo cliente 13/11
B20: 198.25 | C20: SIMMONS ARG | D20: 33840.5 | E20: 0 | F20: =Tabela13[[#This Row],[TOTAL VALUE INVOICE US$]]-Tabela13[[#This Row],[ADVANCE PAYMENT /CREDIT NOTE US$]] -> 33840.5 | G20: PAGA | H20: PAGA | J20: Notificar com fechamento novembro- Notificaciones serán hechas x F&A
B21: 192.25 | C21: PARAÍSO DEL ECUADOR | D21: 12464.3 | E21: 12429.3 | F21: =Tabela13[[#This Row],[TOTAL VALUE INVOICE US$]]-Tabela13[[#This Row],[ADVANCE PAYMENT /CREDIT NOTE US$]] -> 35 | G21: PAGA | H21: PAGA | I21: 13/11/2025 - 24/11 - 26/11 | J21: Notificado - pending
B22: 191.25 | C22: BED TIME | D22: 43413.09 | E22: 43413.09 | F22: =Tabela13[[#This Row],[TOTAL VALUE INVOICE US$]]-Tabela13[[#This Row],[ADVANCE PAYMENT /CREDIT NOTE US$]] -> 0 | G22: PAGA | H22: PAGA | J22: Swift recibido 03/02
B23: 187.25 final | C23: POLYMAX | D23: 1773.88 | F23: =Tabela13[[#This Row],[TOTAL VALUE INVOICE US$]]-Tabela13[[#This Row],[ADVANCE PAYMENT /CREDIT NOTE US$]] -> 1773.88 | G23: JAN/26 | H23: PAGA | I23: 15/01/2026 - 23/02- 03/03 | J23: Ver esquema de pgos
B24: 187.25 | C24: POLYMAX | D24: =30596 -> 30596 | F24: =Tabela13[[#This Row],[TOTAL VALUE INVOICE US$]]-Tabela13[[#This Row],[ADVANCE PAYMENT /CREDIT NOTE US$]] -> 30596 | G24: NOV/25 | H24: PAGA | I24: 15/01/2026 - 23/02 - 03/03 | J24: Pending Notificado - enviar consolidado c/complemento (31.406,39+1,773,88)-saldo despues de carnaval/ Nvo Swift 18Mar- esquema de abonos semanales (fup_)
B25: 180.25 | C25: SUNLOCK SPA | D25: 4734.94 | E25: =3385.14+1349.8 -> 4734.94 | F25: =Tabela13[[#This Row],[TOTAL VALUE INVOICE US$]]-Tabela13[[#This Row],[ADVANCE PAYMENT /CREDIT NOTE US$]] -> 0 | G25: PAGA | H25: PAGA | I25: ago-set- 06/11 - 26/11 - 10/12 - 16/12 - 15/01 -04/02 | J25: SWIFT 23/02
B26: 175.25 | C26: BED TIME | D26: =VLOOKUP(Tabela13[[#This Row],[INVOICE]],'GESTAO CREDITO E PAGAMENTOS'!A$4:R145,11,0) -> 0 | E26: 0 | F26: ='GESTAO CREDITO E PAGAMENTOS'!L34 -> 11129.9 | G26: finalizado | H26: PAGA | I26: paga | J26: email s/ resposta 15/7- PAGA
B27: 174.25 | C27: SUNLOCK SPA | D27: =VLOOKUP(Tabela13[[#This Row],[INVOICE]],'GESTAO CREDITO E PAGAMENTOS'!A$4:R143,11,0) -> 0 | E27: 0 | F27: ='GESTAO CREDITO E PAGAMENTOS'!L33 -> 0 | G27: finalizado | H27: PAGA | I27: 01/07/2025 - 16/07 - 28/07- 05/08 - 06/08-25/08-10/09 | J27: Paga - saldo paga amostras 121.25
B28: 172.25 | C28: DAVID MORENO VISCARRA | D28: 5543.9 | E28: =5283.16+260.74 -> 5543.9 | F28: ='GESTAO CREDITO E PAGAMENTOS'!L30 -> 6438.41 | G28: finalizado | H28: PAGA | I28: 01/07/2025 - 28/07 - 06/08 | J28: Swift recibido 14/08-saldo pendiente recbido 29/08 pago
B29: 171.25 | C29: DIST. CASEROS | D29: =VLOOKUP(Tabela13[[#This Row],[INVOICE]],'GESTAO CREDITO E PAGAMENTOS'!A$4:R146,11,0) -> 0 | E29: 0 | F29: ='GESTAO CREDITO E PAGAMENTOS'!L35 -> 5543.9 | G29: finalizado | H29: PAGA | I29: paga | J29: pagó - swift 05082025 pagA
B30: 165.25 | C30: INMAPOL (Industria de la Madera y el Poliuretano) | D30: 6438.41 | E30: 5906 | F30: ='GESTAO CREDITO E PAGAMENTOS'!L25 -> 0 | G30: finalizado | H30: PAGA | I30: 45764 | J30: Recibido Swift Saldo 28/4. Solicita relatorio comisiones pendientes/rqtd Luciano/ OK - pago
B31: 164.25 | C31: MATERASSI (SEA TRADING) | D31: 1610.82 | E31: 0 | F31: ='GESTAO CREDITO E PAGAMENTOS'!L26 -> 24721.14 | G31: finalizado | H31: PAGA | I31: 45764 | J31: Envio CNPJ- Saldo recebido- email confirmando CR/ OK pago
B32: 161.25+162.25 | C32: CUBA 1 - CUBA 2 | D32: 51274.55 | E32: 38156.36 | F32: =Tabela13[[#This Row],[TOTAL VALUE INVOICE US$]]-Tabela13[[#This Row],[ADVANCE PAYMENT /CREDIT NOTE US$]] -> 13118.19 | G32: JUL/25 | H32: PARCIAL | I32: F-up restrição de cambio-trato direto F&A-CR | J32: Pending - pagos parciais / restrição cambio/ consolida 161.25 + 162.25
B33: 159.25 | C33: PARAÍSO DEL ECUADOR | D33: 29668.52 | E33: 29668.52 | F33: ='GESTAO CREDITO E PAGAMENTOS'!L36 -> 0 | G33: PAGA | H33: PAGA | I33: 13/08, 25/08, 27/08, 03/09-10/09 | J33: paga Swift 18sep
B34: 157.25 | C34: INDUSTRIAS MORENO (HEAVEN) | D34: 10252.8 | E34: 0 | F34: ='GESTAO CREDITO E PAGAMENTOS'!L24 -> 0 | G34: finalizado | H34: PAGA | I34: 45764 | J34: F-up 24/04- sem novos comentários/ Ok - pago
B35: 157.25 | C35: DAVID MORENO VISCARRA | D35: =VLOOKUP(Tabela13[[#This Row],[INVOICE]],'GESTAO CREDITO E PAGAMENTOS'!A4:R19,11,0) -> 0 | E35: 0 | F35: ='GESTAO CREDITO E PAGAMENTOS'!L28 -> 1610.82 | G35: finalizado | H35: PAGA | I35: 45799 | J35: Ok - pago de US$ 15168,15 (3jun25)
B36: 157.25 | C36: SUNLOCK | D36: 5271.96 | E36: 5271.96 | F36: ='GESTAO CREDITO E PAGAMENTOS'!L29 -> 8953.43 | G36: finalizado | H36: PAGA | I36: 45799 | J36: Ok - pago de US$ 5,271,96 (13jun25)
B37: 153.25 | C37: SUNLOCK | D37: =VLOOKUP(Tabela13[[#This Row],[INVOICE]],'GESTAO CREDITO E PAGAMENTOS'!A$4:R143,11,0) -> 0 | E37: 0 | F37: ='GESTAO CREDITO E PAGAMENTOS'!L32 -> 12665.19 | G37: finalizado | H37: PAGA | I37: 01/07/2025 - 16/07 - 28/07- 05/08 - 06/08-25/08 | J37: Pago
B38: 152.25 | C38: FLEX CHILE | D38: 8137.03 | E38: 0 | F38: ='GESTAO CREDITO E PAGAMENTOS'!L31 -> 2222.72 | G38: finalizado | H38: PAGA | I38: 45839 | J38: email- cobrança não procede; pedido nunca foi despachado-devera ser dado de baixa do sist.
B39: 151.25 | C39: FLEX CHILE | D39: =VLOOKUP(Tabela13[[#This Row],[INVOICE]],'GESTAO CREDITO E PAGAMENTOS'!A3:R18,11,0) -> 0 | E39: 0 | F39: ='GESTAO CREDITO E PAGAMENTOS'!L27 -> 63969.62 | G39: finalizado | H39: PAGA | I39: 45799 | J39: pgo confirmado 03Jun/ OK pago
B40: 150.25 | C40: INDUSTRIAS MORENO (HEAVEN) | D40: 4213.29 | E40: 0 | F40: ='GESTAO CREDITO E PAGAMENTOS'!L23 -> 51274.55 | G40: finalizado | H40: PAGA | I40: 45764 | J40: F-up 24/04- sem novos comentários/ Ok - pago
B41: 026.26 + 026.26 C | C41: IND REGAL | D41: 39750 | F41: =Tabela13[[#This Row],[TOTAL VALUE INVOICE US$]]-Tabela13[[#This Row],[ADVANCE PAYMENT /CREDIT NOTE US$]] -> 39750 | G41: AGO/26 | H41: PAGA | I41: Esperar despacho y facturación (atraso) | J41: F-UP Faturamento
B42: 025.26 | C42: MULTIESPUMAS VISCARRA | D42: 9706.74 | E42: 9706.74 | F42: =Tabela13[[#This Row],[TOTAL VALUE INVOICE US$]]-Tabela13[[#This Row],[ADVANCE PAYMENT /CREDIT NOTE US$]] -> 0 | G42: PAGA | H42: PAGA | I42: 01/07/2026 / PAGO 1407 | J42: Pending - Notificado
B43: 024.26 | C43: TEXTIL FIBREX | D43: ='GESTAO CREDITO E PAGAMENTOS'!L106 -> 17828.85 | F43: =Tabela13[[#This Row],[TOTAL VALUE INVOICE US$]]-Tabela13[[#This Row],[ADVANCE PAYMENT /CREDIT NOTE US$]] -> 17828.85 | G43: PAGA | H43: PAGA | J43: Notificar fin de mês
B44: 022.26 | C44: INDUCOL | D44: ='GESTAO CREDITO E PAGAMENTOS'!L105 -> 23876.54 | E44: ='GESTAO CREDITO E PAGAMENTOS'!M105 -> 23876.53 | F44: =Tabela13[[#This Row],[TOTAL VALUE INVOICE US$]]-Tabela13[[#This Row],[ADVANCE PAYMENT /CREDIT NOTE US$]] -> 0.01 | G44: PAGA | H44: PAGA | J44: SWIFTS RECIBIDOS -VR FILE - 0,01 saldo
B45: 016.26 | C45: DIST. CASEROS | D45: =16122.07+2682 -> 18804.07 | F45: =Tabela13[[#This Row],[TOTAL VALUE INVOICE US$]]-Tabela13[[#This Row],[ADVANCE PAYMENT /CREDIT NOTE US$]] -> 18804.07 | G45: JUN/26 | H45: PAGA | I45: Notificado 15/07 | J45: SWIFT 02JUL RECIBIDO 15JUL
B46: 015.26 | C46: BED TIME | D46: 54303.27 | F46: =Tabela13[[#This Row],[TOTAL VALUE INVOICE US$]]-Tabela13[[#This Row],[ADVANCE PAYMENT /CREDIT NOTE US$]] -> 54303.27 | G46: JUN/26 | H46: PAGA | I46: Notificado 15/07 | J46: Notificar
B47: 014.26 | C47: SUPERSPUMA PARAGUAY (SAECA) | D47: 7540.92 | F47: =Tabela13[[#This Row],[TOTAL VALUE INVOICE US$]]-Tabela13[[#This Row],[ADVANCE PAYMENT /CREDIT NOTE US$]] -> 7540.92 | G47: PAGA | H47: PAGA | I47: Esperar despacho - 14 Abril - 100% counter expedition | J47: Swift recibido 21/04
B48: 006.26 + 009.26 | C48: FLEX CHILE | D48: 3711.28 | F48: =Tabela13[[#This Row],[TOTAL VALUE INVOICE US$]]-Tabela13[[#This Row],[ADVANCE PAYMENT /CREDIT NOTE US$]] -> 3711.28 | G48: PAGA | H48: PAGA | J48: pagó swift 28/05 - diferencia negativa de -0,03
B49: 004.26 | C49: SIMMONS ARGENTINA | D49: 22216.2 | F49: =Tabela13[[#This Row],[TOTAL VALUE INVOICE US$]]-Tabela13[[#This Row],[ADVANCE PAYMENT /CREDIT NOTE US$]] -> 22216.2 | G49: PAGA | H49: PAGA | I49: 09/04/2026 - SWIFT 21/02 | J49: pending - notificado/ Simmons efetuará o pagamento 17/04
B50: 003.26+005.26+007.26 | C50: SUNLOCK SPA | D50: 18182.65 | F50: =Tabela13[[#This Row],[TOTAL VALUE INVOICE US$]]-Tabela13[[#This Row],[ADVANCE PAYMENT /CREDIT NOTE US$]] -> 18182.65 | G50: MAR/26 | H50: PENDING-ESPECIAL | I50: Notificados varias veces | J50: Pending - esquema de pagos
B51: 023.26 | C51: PARAÍSO DEL ECUADOR | D51: 8942.78 | E51: 776.08 | F51: =Tabela13[[#This Row],[TOTAL VALUE INVOICE US$]]-Tabela13[[#This Row],[ADVANCE PAYMENT /CREDIT NOTE US$]] -> 8166.7 | G51: JUL/26 | H51: PENDING | I51: Notificado 04/08 - 24/08, 25, 26/08, 28/08/31/08- Aplica NC por problemas QA/acuerdo de pgo semana 30/09 | J51: Pending
B52: 027.26 | C52: LAMITEX S.A. | D52: 13551.35 | F52: =Tabela13[[#This Row],[TOTAL VALUE INVOICE US$]]-Tabela13[[#This Row],[ADVANCE PAYMENT /CREDIT NOTE US$]] -> 13551.35 | G52: PAGA | H52: PAGA | I52: Notificado 04/08 | J52: Notificar
B53: 036.26 | C53: SUPERSPUMA PARAGUAY (SAECA) | D53: 8008.46 | F53: =Tabela13[[#This Row],[TOTAL VALUE INVOICE US$]]-Tabela13[[#This Row],[ADVANCE PAYMENT /CREDIT NOTE US$]] -> 8008.46 | G53: JUL/26 | H53: PAGA | I53: fin julho | J53: PAGO 04/08 SWIFT
B54: 011.26 | C54: SUNLOCK SPA | D54: 24162.66 | E54: 6575.25 | F54: =Tabela13[[#This Row],[TOTAL VALUE INVOICE US$]]-Tabela13[[#This Row],[ADVANCE PAYMENT /CREDIT NOTE US$]] -> 17587.41 | G54: JUL/26 | H54: PENDING-ESPECIAL | I54: Notificados varias veces | J54: Pending - esquema de pagos
B55: 017.26 & 021.26 | C55: POLYMAX EL GALO | D55: 21850.5 | E55: 6000 | F55: =Tabela13[[#This Row],[TOTAL VALUE INVOICE US$]]-Tabela13[[#This Row],[ADVANCE PAYMENT /CREDIT NOTE US$]] -> 15850.5 | G55: JUL/26 | H55: PENDING-ESPECIAL | I55: Notificados varias veces | J55: Pending - Ofrece pago para final agosto - Ver esquema especial
B56: 029.26 | C56: TECNIPONA | D56: 3375.72 | E56: 3146.4 | F56: =Tabela13[[#This Row],[TOTAL VALUE INVOICE US$]]-Tabela13[[#This Row],[ADVANCE PAYMENT /CREDIT NOTE US$]] -> 229.32 | G56: AGO/26 | H56: PAGA - SALDO NEG | I56: muestra recibida (190mts) / sólo saldo pendiente | J56: Pending/ amostra facturavel -pgto efetuado - saldo negativo
B57: 042.26 | C57: SEA TRADING | D57: 3729.08 | E57: 525 | F57: =Tabela13[[#This Row],[TOTAL VALUE INVOICE US$]]+Tabela13[[#This Row],[ADVANCE PAYMENT /CREDIT NOTE US$]] -> 4254.08 | G57: SET/26 | H57: PAGA | I57: Notificar- Fup faturamento e coleta | J57: Pending - ok swift
B58: 039.26 +041.26+049.26 | C58: MULTIESPUMAS VISCARRA | D58: 12400.4 | F58: =Tabela13[[#This Row],[TOTAL VALUE INVOICE US$]]-Tabela13[[#This Row],[ADVANCE PAYMENT /CREDIT NOTE US$]] -> 12400.4 | G58: OUT/26 | H58: PENDING | I58: ajuste de terminos pago 30 días | J58: Pending
G59: SEP/26
F60: ='GESTAO CREDITO E PAGAMENTOS'!L79 -> 6554.95
D67: =21850.5+297 -> 22147.5

Sheet SUNLOCK SPA -flujo crédito1906 
A1: GESTIÓN DE CRÉDITO Y PAGOS - 2025 / 2026 | D1: =TODAY() -> 46296
S3: =SUM(I6:I8)-K6 -> 31030.95
A4: PROFORMA-INVOICE (EXPORT.) | B4: CLIENTE | C4: N° ORDEN | D4: FECHA PROFORM | E4: FECHA COLECTA | F4: TERMINO PAGO | G4: days | H4: FECHA VENCIMENTO/ DEADLINE | I4: TOTAL A PAGAR SEGÚN INVOICE US$ | J4: ANTICIPO (US$) | K4: NOTA CREDITO US$ | L4: PAGO FINAL US$ | M4: TOTAL SALDO DEBIDO HOY (US$) | N4: STATUS PAGO | O4: FECHA DE PAGO | P4: DIAS ATRASO | Q4: OBSERV. | S4: pagos 1er ac. | T4: pagos 2do ac
A5: 174.25 | B5: SUNLOCK SPA | C5: 6940 | D5: 45772 | E5: 45817 | F5: 30 days | G5: 30 | H5: 45847 | I5: 13839.68 | L5: 13839.68 | M5: =SUM(J5:L5)-I5 -> 0 | N5: paga | O5: 45947 | P5: =O5-H5 -> 100 | Q5: SWIFT 17Oct POR $13.839,68 | S5: 14591.42 | T5: 6575.25
A6: 180.25 | B6: SUNLOCK SPA | C6: 7173 | D6: 45805 | E6: 45855 | F6: 30 days | G6: 30 | H6: 45885 | I6: 4734.94 | K6: 3385.14 | L6: 14591.42 | M6: =SUM(J6:L6)-I6 -> 13241.62 | N6: paga | O6: 46076 | P6: =O6-H6 -> 191 | Q6: SWIFT 23/02 por $14.591,42 - aplicação NC 3385,14 | S6: 5597.15
A7: 209.25 + 210.25 | B7: SUNLOCK SPA | C7: 8569/8798/8609 | D7: 45937 | E7: 45968 | F7: 30 days | G7: 30 | H7: 45998 | I7: 13908.91 | J7: =M6 -> 13241.62 | L7: 5659.15 | M7: =SUM(J7:L7)-I7 -> 4991.86 | N7: paga | O7: 46136 | P7: =O7-H7 -> 138 | Q7: Saldo anterior ($13.241,62) + SWIFT 24/04 ($5659,15) | S7: 5597.15
A8: 220.25 © | B8: SUNLOCK SPA | C8: 9030 /9035 | D8: 45985 | E8: 46010 | F8: 30 days | G8: 30 | H8: 46040 | I8: =15772.24 -> 15772.24 | J8: =M7 -> 4991.86 | L8: =5597.15+5592.15 -> 11189.3 | M8: =SUM(J8:L8)-I8 -> 408.92 | N8: paga | O8: 46191 | P8: =O8-H8 -> 151 | Q8: saldo anterior (4.991,86) + SWIFT 01/06 (5597,15) +SWIFT 18/06 ($5.592,15) | S8: 5659.15
A9: 003.26+ 005.26 + 007.26 | B9: SUNLOCK SPA | C9: 9157/9177/9207 | D9: 46010 | E9: 46073 | F9: 30 days | G9: 30 | H9: 46103 | I9: 18182.65 | J9: =408.92 -> 408.92 | L9: =5659.15+21013.51 -> 26672.66 | M9: =SUM(J9:L9)-I9 -> 8898.93 | N9: paga | O9: 46283 | P9: =O9-H9 -> 180 | Q9: Saldo anterior $408,91 + SWIFT 12/08 ($5.659,15)+SWIFT 18/09 $21.013,51 | S9: =SUM(S5:S8) -> 31444.87 | T9: =SUM(T5:T8) -> 6575.25
A10: 011.26 | B10: SUNLOCK SPA | C10: 9522 | D10: 46077 | E10: 46140 | F10: 30 days | G10: 30 | H10: 46230 | I10: 24162.66 | J10: =8898.93+6575.25 -> 15474.18 | M10: =SUM(J10:L10)-I10 -> -8688.48 | N10: parcial | O10: 46146 | P10: =O10-H10 -> -84 | Q10: Incluye frete |saldo sobrante anterior ($8.898,93)+ SWIFT 04/05 $6.575,25 | S10: =S3-S9 -> -413.92
A11: 032.26* | B11: SUNLOCK SPA | C11: 10497 | D11: 46182 | E11: 46293 | F11: 30 days | H11: 46293 | I11: 16234.12 | M11: =SUM(J11:L11)-I11 -> -16234.12 | N11: pendente | O11: 46293 | P11: =O11-H11 -> 0 | Q11: Fup pgtos (pedido on hold será liberado 28/09 )|inclui frete
L12: Total | M12: =SUM(M10:M11) -> -24922.6
A14: **pedido estuvo on hold-ya despachado 22/09
A18: 1) *Invoices antiguas 180.25/209.25/210.25 /220.25 (deuda de $31.030,95) - 1er Acuerdo (19marzo) de pagar en 6 cuotas de USD | K18: =SUM(I6:I8)-K6 -> 31030.95 | L18: =K18/6 -> 5171.825
A20: Esquema de pagos: | B20: Pago | C20: Dif | D20: Index | E20: balance hoy
A21: 46136 | B21: 5597.15
A22: 46174 | B22: =5597.15 -> 5597.15
A23: 46191 | B23: 5592.15 | E23: =K18-(SUM(B21:B23)) -> 14244.5
A24: 46246 | B24: 5659.15
A26: 2)**Última Invoice 011.26 | B26: =I10 -> 24162.66 | C26: - Condiciones de pago especiales(29/4/26) > | H26: 33% anticipado /33% 30d /33% 60d
A28: Esquema de pagos: | B28: Pago | C28: Dif. | D28: Index | E28: Invoice | H28: Observ. | I28: Balance
A29: 46146 | B29: 6575.25 | D29: =B29/24162.66 -> 0.27212443 | E29: 011.26 | H29: 1er Abono | I29: =I10-B29 -> 17587.41
A30: 46179 | H30: atraso
A31: 46210 | H31: atraso
A34: 3) Nueva propuesta de pago colocada por el cliente via email (03/09/2026) - En proceso de aprobación interna
A36: Propuesta :
A37: Con Fecha 04/09/2026 se paga USD 17.235,78 ( Orden Fabricada )
A38: Quedando un Saldo de USD 30.110,90, de este saldo se pagan USD 3.777,73 Mensual hasta Diciembre, | N38: 47346.69
A39: sumando estos 4 meses nos da USD 15.110,92 y Finalmente en Diciembre se paga el Saldo Final de USD 15.000 . | M39: - | N39: 17235.78 | O39: =N38-N39 -> 30110.91 | P39: sep | Q39: =17235.78+3777.73 -> 21013.51
M40: - | N40: 4x3777,73 | O40: =4*3777.73 -> 15110.92 | P40: sep/oct/nov/dic
A41: Propuesta Interna (04/09) | O41: =O39-O40 -> 14999.99 | P41: dic | Q41: =15000+3777.73 -> 18777.73
A42: USD 17.235,78 correspondientes a la orden fabricada; y | P42: *contraints (sep & dec)
A43: USD 15.000,00 como amortización de la deuda pendiente.
A44: saldo restante de USD 15.110,90 podríamos mantenerlo dentro de un calendario de pagos en 6 cuotas. Hasta marzo de 2027

Sheet POLYMAX -flujo de crédito 1805
A1: POLYMAX EL GALO | E1: =TODAY() -> 46296
A4: INVOICE (EXPORT.) | B4: CUSTOMER | C4: ORDER NBR | D4: DATA PROFORM-INVOICE | E4: DATA COLETA (ESTIMADA) | F4: TERMINO PAGO | G4: FECHA VENCIMENTO/ DEADLINE | H4: TOTAL A PAGAR SEGÚN INVOICE US$ | I4: ANTICIPO (US$) | J4: NOTA CREDITO US$ | K4: ABONOS US$ | L4: TOTAL CREDITOS US$ | M4: TOTAL SALDO DEBIDO HOY (US$) | N4: STATUS PAGO | O4: FECHA DE PAGO | P4: DIAS ATRASO | Q4: OBSERV.
A5: 187.25 | B5: POLYMAX EL GALO | C5: 7523/8302 | D5: 45848 | E5: 45917 | F5: 60 days | G5: 45977 | H5: =30596 -> 30596 | I5: 15000 | K5: =7978.5+6978.5+6965 -> 21922 | L5: =SUM(I5:K5) -> 36922 | M5: =L5-H5 -> 6326 | N5: paga | O5: 46154 | P5: =$E$1-G5 -> 319 | Q5: SWiFTs 03Feb26 ($15K)+18Mar ($7.978,50)+24/03 ($ 6.978,5)+12May ($6695) cobre saldos 187.25/Final + parcial 215.
A6: 187.25 Final | B6: POLYMAX EL GALO | C6: 7523 | D6: 45962 | E6: 45987 | F6: 60 days | G6: 46047 | H6: 1773.88 | K6: =M5 -> 6326 | L6: =SUM(I6:K6) -> 6326 | M6: =L6-H6 -> 4552.12 | N6: paga | O6: 46154 | P6: =$E$1-G6 -> 249 | Q6: SWIFT 12/05 $6695- arriba utilizado para cobrir saldo
A7: 215.25 | B7: POLYMAX EL GALO | C7: 8811 | D7: 45964 | E7: 46007 | F7: 60 days | G7: 46067 | H7: 13678.46 | K7: =3633.73+10044+0.73 -> 13678.46 | L7: =SUM(I7:K7) -> 13678.46 | M7: =L7-H7 -> 0 | N7: paga | O7: 46293 | P7: =$E$1-G7 -> 229 | Q7: Saldo SWIFT 12/05 arriba abona parcialmente esta invoice|SWIFT 15jun (10.044,00) cierra cuenta/ saldado 0,73 del swift de 28/09
A8: 017.26 & 021.26 | B8: POLYMAX EL GALO | C8: 9747 | D8: 46094 | E8: 46148 | F8: 60 days | G8: 46208 | H8: 21850.5 | K8: =6000+8000+8000-0.73 -> 21999.27 | L8: =SUM(I8:K8) -> 21999.27 | M8: =L8-H8 -> 148.77 | N8: paga | O8: 46293 | P8: =$E$1-G8 -> 88 | Q8: consolida con 021.26 / considerar $108 como juros/taxa - saldar | SWIFT 17/07 $6000+ SWIFT 10Sep $8.000+SWIFT 28/09 $8.000
A9: 053.26 | B9: POLYMAX EL GALO | C9: 11186 | D9: 46260 | E9: 46300 | G9: 46360 | H9: 19243 | I9: 148.77 | L9: =SUM(I9:K9) -> 148.77 | M9: =L9-H9 -> -19094.23 | N9: Futura | O9: 46360 | P9: =$E$1-G9 -> -64 | Q9: pedido nuevo en curso
E14: PGO | F14: Pendente | G14: Saldo | H14: Invoice ref.
A15: Nuevo pago parcial 12/05/2026 | D15: $6965 | E15: 6965 | F15: 1557.39 | G15: =E15-F15 -> 5407.61 | H15: 187.25
F16: 1773.88 | G16: =G15-F16 -> 3633.73 | H16: 187.25 final
E17: =E15-F15-F16 -> 3633.73 | F17: 13678.46 | G17: =F17-E17 -> 10044.73 | H17: 215.25
A18: Nuevo pago 15/06/2026 | D18: $10044 | E18: 10044 | G18: 0.73 | H18: 215.25
A25: pagos em mi ausencia
A26: 46275 | B26: 8000

Sheet Banking Data Conexao

Sheet SUNLOCK-flujo de credito 180526
A1: GESTIÓN DE CRÉDITO Y PAGOS - 2025 / 2026 | D1: =TODAY() -> 46296
S3: =SUM(I6:I8) -> 34416.09
A4: PROFORMA-INVOICE (EXPORT.) | B4: CLIENTE | C4: N° ORDEN | D4: FECHA PROFORM | E4: FECHA COLECTA | F4: TERMINO PAGO | G4: days | H4: FECHA VENCIMENTO/ DEADLINE | I4: TOTAL A PAGAR SEGÚN INVOICE US$ | J4: ANTICIPO (US$) | K4: NOTA CREDITO US$ | L4: PAGO FINAL US$ | M4: TOTAL SALDO DEBIDO HOY (US$) | N4: STATUS PAGO | O4: FECHA DE PAGO | P4: DIAS ATRASO | Q4: OBSERV. | S4: pagos 1er ac. | T4: pagos 2do ac
A5: 174.25 | B5: SUNLOCK SPA | C5: 6940 | D5: 45772 | E5: 45817 | F5: 30 days | G5: 30 | H5: 45847 | I5: 13839.68 | L5: 13839.68 | M5: =SUM(J5:L5)-I5 -> 0 | N5: paga | O5: 45947 | P5: =O5-H5 -> 100 | Q5: SWIFT 17Oct POR $13.839,68 | S5: 14591.42 | T5: 6575.25
A6: 180.25 | B6: SUNLOCK SPA | C6: 7173 | D6: 45805 | E6: 45855 | F6: 30 days | G6: 30 | H6: 45885 | I6: 4734.94 | K6: 3385.14 | L6: =Tabla7[[#This Row],[TOTAL A PAGAR SEGÚN INVOICE US$]]-K6 -> 1349.8 | M6: =SUM(J6:L6)-I6 -> 0 | N6: paga | O6: 46076 | P6: =O6-H6 -> 191 | Q6: SWIFT 23/02 por $14.591,42 - menos NC 3385,14 | S6: 5597.15
A7: 209.25 + 210.25 | B7: SUNLOCK SPA | C7: 8569/8798/8609 | D7: 45937 | E7: 45968 | F7: 30 days | G7: 30 | H7: 45998 | I7: 13908.91 | J7: 13908.91 | L7: =14591.42-1349.8+667.29 -> 13908.91 | M7: =J7-I7 -> 0 | N7: paga | O7: 46136 | P7: =O7-H7 -> 138 | Q7: Saldo de SWIFT 23/02 ($14.591,42) cubre parcialmente + SWIFT 24/04 $5597,15 cierra cuenta | S7: 5597.15
A8: 220.25 © | B8: SUNLOCK SPA | C8: 9030 /9035 | D8: 45985 | E8: 46010 | F8: 30 days | G8: 30 | H8: 46040 | I8: 15772.24 | J8: =4991.86 -> 4991.86 | L8: 5597.15 | M8: =SUM(J8:L8)-I8 -> -5183.23 | N8: parcial | O8: =TODAY() -> 46296 | P8: =O8-H8 -> 256 | Q8: Incluye flete|Swift 24/04 - credito parcial| SWIFT 01/06 (5597,15) abono parcial
A9: 003.26+ 005.26 + 007.26 | B9: SUNLOCK SPA | C9: 9157/9177/9207 | D9: 46010 | E9: 46073 | F9: 30 days | G9: 30 | H9: 46103 | I9: 18182.65 | M9: -18182.65 | N9: pendiente | O9: =TODAY() -> 46296 | P9: =O9-H9 -> 193 | Q9: marzo'26 | S9: =SUM(S5:S8) -> 25785.72 | T9: =SUM(T5:T8) -> 6575.25
A10: 011.26 | B10: SUNLOCK SPA | C10: 9522 | D10: 46077 | E10: 46140 | F10: 30 days | G10: 30 | H10: 46230 | I10: 24162.66 | J10: 6575.25 | M10: -17587.41 | N10: parcial | O10: 46230 | P10: =O10-H10 -> 0 | Q10: julho'26 - final| Incluye frete | SWIFT 04/05 $6.575,25 | S10: =S3-S9 -> 8630.37
I13: =SUM(I6:I8) -> 34416.09 | J13: urgent | K13: acuerdo de pago em 6X
I14: =I9 -> 18182.65 | J14: marzo | K14: pendiente?
I15: =I10 -> 24162.66 | J15: julio | K15: acuerdo pago de 33%-33%-33%
A19: 1) Acuerdo de pagar en 6 cuotas de USD 5.777,03 (19/03 - 06/04)
A20: =6*5777.03 -> 34662.18
A21: Esquema de pagos: | I21: Observ.
A22: 46136 | B22: 5659.15 | C22: =B22-5777.03 -> -117.88 | D22: =B22/5777.03 -> 0.97959505 | E22: ok 209/210- parcial 220.25 | I22: =5659.15-667.29 -> 4991.86 | J22: error em deuda total según carta de pagos recibida 27/04
A26: 2)Última Invoice 011.26 - Condiciones de pago especiales(29/04/26)
A27: 33% anticipado 33% 30d 33% 60
A28: =I10*33% -> 7973.6778 | B28: OK - 1ER ABONO | D28: =6575.25/I10 -> 0.27212443
A31: 1) *Invoices antiguas 180.25/209.25/210.25 /220.25 (deuda de $34.416,09) - Acuerdo de pagar en 6 cuotas de USD | I31: =34416.09/6 -> 5736.015 | J31: (19/03/2026)
A33: Esquema de pagos: | B33: Pago | C33: Dif | D33: Index | E33: Invoice(s) | H33: Observ. | I33: Balance
A34: 46136 | B34: 5597.15 | C34: =B34-$I$31 -> -138.865 | D34: =B34/$I$31 -> 0.97579068 | E34: 180/209/210 + parcial 220.25 | H34: Dif.de pago vs cuota | I34: =I13-B34 -> 28818.94
A35: 46174 | B35: =5597.15 -> 5597.15 | C35: =B35-$I$31 -> -138.865 | D35: =B35/$I$31 -> 0.97579068 | E35: 180/209/210 + parcial 220.25 | H35: sender charge 62+30 | I35: =I34-B35 -> 23221.79
A41: 2)**Última Invoice 011.26 | B41: =I10 -> 24162.66 | C41: - Condiciones de pago especiales(29/4/26) > | F41: 33% anticipado /33% 30d /33% 60 | J41: 8793.7 | K41: =B41*33% -> 7973.6778
A43: Esquema de pagos: | B43: Pago | C43: Dif. | D43: Index | E43: Invoice | H43: Observ. | I43: Balance
A44: 46146 | B44: 6575.25 | D44: =B44/24162.66 -> 0.27212443 | E44: 011.26 | H44: 1er Abono | I44: =I10-B44 -> 17587.41
D49: =5841.47*4 -> 23365.88
D55: =6575.25+8793.7+8793.7 -> 24162.65

Sheet Hoja1
A5: PROFORMA-INVOICE (EXPORT.) | B5: CLIENTE | C5: FECHA COLECTA | D5: TERMINO PAGO | E5: FECHA VENCIMENTO/ DEADLINE | F5: TOTAL A PAGAR SEGÚN INVOICE US$ | G5: ANTICIPO (US$) | H5: NOTA CREDITO US$ | I5: PAGO FINAL US$ | J5: TOTAL SALDO DEBIDO HOY (US$) | K5: STATUS PAGO | L5: FECHA DE PAGO | M5: DIAS ATRASO | N5: OBSERV.
A6: 209.25 + 210.25 | B6: SUNLOCK SPA | C6: 45968 | D6: 30 days | E6: 45998 | F6: 13908.91 | G6: 13241.62 | I6: 13241.62 | J6: -667.29 | K6: parcial | L6: 46076 | M6: 101 | N6: SWIFT 23/02 cubre parcialmente
A7: 220.25 | B7: SUNLOCK SPA | C7: 46010 | D7: 30 days | E7: 46040 | F7: 15772.24 | J7: -15772.24 | K7: pendiente | L7: 46099 | M7: 59 | N7: Incluye flete
A8: 003.26+ 005.26 + 007.26 | B8: SUNLOCK SPA | C8: 46073 | D8: 30 days | E8: 46103 | F8: 18182.65 | J8: -18182.65 | K8: pendiente | L8: 46099 | N8: marzo'26
A9: 011.26 | B9: SUNLOCK SPA | C9: 46112 | D9: 30 days | E9: 46142 | F9: 19925 | J9: -19925 | K9: futura | L9: 46099 | N9: abril'26

Sheet FLEX  CHILE
A1: Detalles de Suma de TOTAL DUE BALANCE (US$) - CLIENTE: FLEX CHILE, RECIB. PGTO: futura
A3: INVOICE (EXPORT.) | B3: CLIENTE | C3: PEDIDO TOTVS | D3: DATA INVOICE | E3: DATA COLETA | F3: PAYMENT TERMS | G3: days | H3: DATA VENCIMENTO/ DEADLINE | I3: TOTAL DUE PAYMENT-AS PER INVOICE US$ | J3: ADVANCE PAYMENT (US$) | K3: TOTAL DUE BALANCE (US$) | L3: VALOR TOTAL R$ | M3: NÚMERO NF | N3: RECIB. PGTO | O3: OBSERV.
A4: 183.25 | B4: FLEX CHILE | C4: (7178 / 7234) | D4: 45810 | E4: 45838 | F4: 90 Days | G4: 90 | H4: 45928 | I4: 11960 | J4: 11960 | K4: 0 | L4: 41676.25 | M4: 58965 | N4: futura | O4: (11.960,00) - Devolução cliente processada 23/07 -NF 059.324 - R$ 41.676,25
A5: 181.25 | B5: FLEX CHILE | C5: 7178/6880/7015 | D5: 45806 | E5: 45837 | F5: 90 Days | G5: 90 | H5: 45927 | I5: 7360 | J5: 7360 | K5: 0 | L5: - | M5: 58965 | N5: futura | O5: faturado / 6880 / 7015 -- Invoice saida 167.25+168.25+181.25 (12.665,19) - 7.360,00
A6: 163.25 | B6: FLEX CHILE | C6: 6752 / 6868 / 6949 | D6: 45754 | E6: 45792 | F6: 90 Days | G6: 90 | H6: 45882 | K6: 0 | L6: - | M6: 58048/57.898 | N6: futura | O6: 6752 / 6868 / 6949; ajustada para 164.25. Ver valores nessa cell
A7: 176.25 | B7: FLEX CHILE | C7: 6949 | D7: 45776 | E7: 45792 | F7: 90 Days | G7: 90 | H7: 45882 | I7: 1840 | K7: 1840 | L7: - | N7: futura | O7: parcialmente atendido
A8: 166.25 | B8: FLEX CHILE | C8: 6875 | D8: 45754 | E8: 45771 | F8: 90 Days | G8: 90 | H8: 45861 | I8: 2222.72 | K8: 2222.72 | L8: 12642.83 | M8: 57775 | N8: futura | O8: will Charge--Rep. Qualidade. 2.222,72
A9: 168.25 | B9: FLEX CHILE | C9: 6880 / 7015 | D9: 45784 | E9: 45814 | F9: 90 Days | G9: 90 | H9: 45904 | I9: 3375 | K9: 3375 | L9: - | M9: - | N9: futura | O9: 167+168+181 - inv 167.25 + 168.25 juntas para faturamento - Fup
A10: 189.25 | B10: FLEX CHILE | C10: 7630 | D10: 45848 | E10: 45879 | F10: 90 Days | G10: 90 | H10: 45969 | I10: 4123 | K10: 4123 | N10: futura
A11: 167.25 | B11: FLEX CHILE | C11: 6880/ 7178 | D11: 45769 | E11: 45807 | F11: 90 Days | G11: 90 | H11: 45897 | I11: 12665.19 | K11: 12665.19 | L11: 71657.84 | M11: 58433/58.358 | N11: futura | O11: 167+168+181/ add +400/+200 dos mesmos artigos 19/5 (125.25 amostras)
A12: 164.25 | B12: FLEX CHILE | C12: 6752 / 6868 / 6949/6816 /6623 | D12: 45777 | E12: 45792 | F12: 90 Days | G12: 90 | H12: 45882 | I12: 63969.62 | K12: 63969.62 | L12: 414202.66 | M12: 58048/57.898/57.985/57.984 | N12: futura | O12: PV 6752 / 6868 / 6949

Sheet DIVINO
A1: Detalles de Suma de TOTAL DUE BALANCE (US$) - CLIENTE: DIVINO, RECIB. PGTO: futura
A3: INVOICE (EXPORT.) | B3: CLIENTE | C3: PEDIDO TOTVS | D3: DATA INVOICE | E3: DATA COLETA | F3: PAYMENT TERMS | G3: days | H3: DATA VENCIMENTO/ DEADLINE | I3: TOTAL DUE PAYMENT-AS PER INVOICE US$ | J3: ADVANCE PAYMENT (US$) | K3: TOTAL DUE BALANCE (US$) | L3: VALOR TOTAL R$ | M3: NÚMERO NF | N3: RECIB. PGTO | O3: OBSERV.
A4: 184.25 | B4: DIVINO | C4: 7235 (7068 / 7235) | D4: 45810 | E4: 45840 | F4: 50% Pre Payment - 50% After Received | G4: 30 | H4: 45870 | I4: 30148.81 | K4: 30148.81 | L4: 165091.87 | M4: 58963 | N4: futura | O4: despacho junto c/173.25 e 177.25/ Invoice revisada 02Jul -(esta Inv.- 30.148,81)
A5: 188.25 | B5: DIVINO | C5: 7503 | D5: 45840 | E5: 45871 | F5: 50% Pre Payment - 50% After Received | G5: 30 | H5: 45901 | I5: 58465 | K5: 58465 | N5: futura | O5: Alteraçã valor proforma por alteração código artigo
A8: NUEVO SWIFT
A9: 17563.81 | B9: 45848 | C9: Cual Invoice????

Sheet template de comunicação
A1: Señores __________
A3: Buenos días Estimados ______,
A5: Informo que el (los) siguiente(s) pedido(s) ya ha(n) sido despachados y quedamos atentos a la confirmación del (los) respectivo(s) pago(s) con copia del documento SWIFT:
A7: INVOICE | B7: TOTAL VALUE $ | C7: ADVANCE PAYMENT | D7: TOTAL DUE BALANCE
A10: Anexo documento con la información sobre los detalles bancarios y copia de la factura.
A12: Mil Gracias de antemano por su atención. Quedamos a su disposición.
A14: Cordiales Saludos,

Sheet contatos chaves
A1: CONEXÃO MALHAS - CONTATOS CHAVES / CLIENTES ATIVOS
A3: Regiao | B3: Sub-regiao | C3: Clientes | D3: Ativos | E3: Inativos | F3: Prospect | G3: Potencial | H3: Estrategicos | I3: Sensiveis | J3: contato | K3: cargo | L3: email | M3: telefone | N3: Observ.
A4: Chile | B4: Santiago | C4: Flex Equipos de Descanso | D4: Sim | E4: - | F4: - | G4: Grande | H4: Sim | I4: Sim | J4: Paulina Mena | K4: Compras | L4: paulina.mena@flex.es | M4: 56 96205 0626 | N4: amostras/ desenvolvimento/OC
A5: Chile | B5: Santiago | C5: Flex Equipos de Descanso | D5: Sim | G5: Grande | H5: Sim | I5: Sim | J5: Danae Briones | K5: Importações | L5: danae.briones@flex.es | M5: +56 9 5514 2584
A6: Chile | B6: Santiago | C6: Flex Equipos de Descanso | D6: Sim | G6: Grande | H6: Sim | I6: Sim | J6: Francesca Seitz | K6: Marketing | L6: francesca.seitz@flex.es | M6: +56 9 3451 9331
A7: Chile | B7: Santiago | C7: Flex Equipos de Descanso | D7: Sim | G7: Grande | H7: Sim | I7: Sim | J7: Angelo Almonacid | K7: Supply | L7: angelo.almonacid@flex.es | M7: +56 9 4400 6214 | N7: Manager of others
A8: Chile | B8: Santiago | C8: Sunlock (Serta) | D8: Sim | E8: - | F8: - | G8: Pequeno | H8: - | I8: - | J8: Juan Carlos Villarroel | K8: Compras | L8: jcvillarroel@sunlock.cl | M8: (+56) 98529-7739
A9: Chile | B9: Santiago | C9: Sunlock (Serta) | D9: Sim | G9: Pequeno | H9: - | I9: - | J9: Felipe San Martin | K9: Socio | L9: fsanmartin@multimetal.cl | M9: +56 9 9939 1194 | N9: Estrategico/ pagamentos
A10: Chile | B10: Santiago | C10: Muebles MPR | D10: Sim | E10: - | F10: - | G10: Pequeno | H10: - | I10: - | J10: Misael | K10: Financeiro | L10: NA | M10: +56 9 5413 0257
A11: Chile | B11: Santiago | C11: Muebles MPR | D11: Sim | G11: Pequeno | H11: - | I11: - | J11: Daniel Carvajal | K11: Socio | L11: mpr.muebleria@gmail.com | M11: +56 9 7977 0882
A12: Paraguai | B12: Asuncao | C12: SuperSpuma | D12: Sim | E12: - | F12: - | G12: Medio | H12: - | I12: - | J12: Leticia Roig | K12: Compras | L12: leticia.roig@superspuma.com.py | M12: +595 985 629024
A13: Paraguai | B13: Asuncao | C13: SuperSpuma | D13: Sim | E13: - | F13: - | G13: Medio | H13: - | I13: - | J13: Maria Laura | K13: Marketing | L13: maria.laura@superspuma.com.py | M13: +595 986 154856
A14: Paraguai | B14: Asuncao | C14: SuperSpuma | D14: Sim | E14: - | F14: - | G14: Medio | H14: - | I14: - | J14: Ruth Sosa | K14: Importações | L14: ruth.sosa@superspuma.com.py | M14: +595 971 889820
A15: Paraguai | B15: Asuncao | C15: Inmapol (Industria de la madera) | D15: Sim | E15: - | F15: - | G15: Pequeno | H15: - | I15: - | J15: Marcos | K15: Socio | L15: madrisa@inmapol.com.py | M15: 595 21 942 599
A16: Paraguai | B16: Asuncao | C16: Inmapol (Industria de la madera) | D16: Sim | E16: - | F16: - | G16: Pequeno | H16: - | I16: - | J16: Alejandro Abraham | K16: Representante | L16: ale@erwinabraham.com | M16: +595 981 485190 | N16: intermediario
A17: Paraguai | B17: Luque | C17: Materassi (Sea Trading) | D17: Sim | E17: - | F17: - | G17: Pequeno | H17: - | I17: - | J17: Alcibiades Greco | K17: Socio | L17: unicornio_py@yahoo.es | M17: 595 982 119084
A18: Paraguai | B18: Luque | C18: Materassi (Sea Trading) | D18: Sim | E18: - | F18: - | G18: Pequeno | H18: - | I18: - | J18: Yessica | K18: Compras | L18: Yessicanuf@gmail.com | M18: NA
A19: Paraguai | B19: Santa Rita | C19: Nature (NM Espuma) | D19: Sim | E19: - | F19: - | G19: Pequeno | H19: - | I19: - | J19: Federico Nuñez | K19: Financeiro | L19: federico@nunez.com.py | M19: +595 983 603791
A20: Paraguai | B20: Santa Rita | C20: Nature (NM Espuma) | D20: Sim | E20: - | F20: - | G20: Pequeno | H20: - | I20: - | J20: Jorge Nuñez | K20: Socio | L20: jorge@nunez.com.py | M20: +595 983 688644
A21: Paraguai | B21: Santa Rita | C21: Nature (NM Espuma) | D21: Sim | E21: - | F21: - | G21: Pequeno | H21: - | I21: - | J21: Susana Diaz | K21: Compras | L21: administracion@nature.com.py | M21: +595 982 795064 | N21: admin
A22: Argentina | B22: Buenos Aires | C22: Simmons Argentina | D22: Sim | E22: - | F22: - | G22: Grande | H22: Sim | I22: Sim | J22: Martin Miller | K22: Representante | L22: comercial@martinmiller.com.ar | M22: +54 9 11 6237-7072 | N22: intermediario
A23: Uruguai | B23: Montevideo | C23: Divino | D23: Sim | E23: - | F23: - | G23: Grande | H23: Sim | I23: Sim | J23: FRANCO MACHAO | K23: Comex | L23: franco.machao@divino.com.uy | M23: + 598 (2) 506.1262
A24: Uruguai | B24: Montevideo | C24: Divino | D24: Sim | E24: - | F24: - | G24: Grande | H24: Sim | I24: Sim | J24: Agustina Vuco | K24: Comex | L24: agustina.vuco@divino.com.uy | M24: +598 98 456 659
A25: Uruguai | B25: Montevideo | C25: Divino | D25: Sim | E25: - | F25: - | G25: Grande | H25: Sim | I25: Sim | J25: Emilia Torres | K25: Comex | L25: emilia.torres@divino.com.uy | M25: +598 98 455 154 | N25: comex@divino.com.uy
A26: Uruguai | B26: Montevideo | C26: Divino | D26: Sim | E26: - | F26: - | G26: Grande | H26: Sim | I26: Sim | J26: Esteban Saibene | K26: Compras | L26: esteban.saibene@divino.com.uy | M26: +598 92 873 272 | N26: Moveis
A27: Uruguai | B27: Montevideo | C27: Divino | D27: Sim | E27: - | F27: - | G27: Grande | H27: Sim | I27: Sim | J27: Federico Durán | K27: Operações | L27: federico.duran@divino.com.uy | M27: +598 99 919 936 | N27: Gte Gral Fabrica
A28: Uruguai | B28: Montevideo | C28: Divino | D28: Sim | E28: - | F28: - | G28: Grande | H28: Sim | I28: Sim | J28: Fernando Rugiero | K28: Compras | L28: fernando.rugiero@divino.com.uy | M28: +598 92 622 679 | N28: Tecido
A29: Uruguai | B29: Montevideo | C29: Divino | D29: Sim | E29: - | F29: - | G29: Grande | H29: Sim | I29: Sim | J29: Francisco Studer | K29: Comex | L29: francisco.studer@divino.com.uy | M29: +598 92 815 133 | N29: Manager of others
A30: Uruguai | B30: Montevideo | C30: Divino | D30: Sim | E30: - | F30: - | G30: Grande | H30: Sim | I30: Sim | J30: Hernán Berro | K30: Supply | L30: hernan.berro@divino.com.uy | M30: +598 98 988 226 | N30: Director
A31: Uruguai | B31: Montevideo | C31: Divino | D31: Sim | E31: - | F31: - | G31: Grande | H31: Sim | I31: Sim | J31: Cecilia Solodilin | K31: Compras | L31: cecilia.solodilin@divino.com.uy | M31: +59825061262 | N31: Asistente de Fernando Rugiero
A32: Uruguai | B32: Montevideo | C32: Polymax | D32: Sim | E32: - | F32: - | G32: Medio | H32: Sim | I32: Sim | J32: Gonzalo Rodriguez | K32: Gerente Gral | L32: grodriguez@polymax.com.uy | M32: +598 2320 2320
A33: Uruguai | B33: Montevideo | C33: Polymax | D33: Sim | E33: - | F33: - | G33: Medio | H33: Sim | I33: Sim | J33: Eliana Garyalde | K33: Asistente Gerencia | L33: asistente.gerencia@polymax.com.uy | M33: +598 94 507 590
A34: Equador | B34: Guayaquil | C34: Productos Paraiso do Ecuador | D34: Sim | E34: - | F34: - | G34: Grande | H34: Sim | I34: - | J34: Diego Perez | K34: Operações | L34: diegoperez@paraiso.com.ec | M34: +593 98 728 8947 | N34: Gte Gral Fabrica
A35: Equador | B35: Guayaquil | C35: Productos Paraiso do Ecuador | D35: Sim | E35: - | F35: - | G35: Grande | H35: Sim | I35: - | J35: Francisco Rivas | K35: Marketing | L35: gerencia.c@paraiso.com.ec | M35: +593 99 440 2827
A36: Equador | B36: Guayaquil | C36: Productos Paraiso do Ecuador | D36: Sim | E36: - | F36: - | G36: Grande | H36: Sim | I36: - | J36: Jose Luis Andrango | K36: Compras | L36: joseandrango@paraiso.com.ec | M36: +593 99 161 0288
A37: Equador | B37: Guayaquil | C37: Productos Paraiso do Ecuador | D37: Sim | E37: - | F37: - | G37: Grande | H37: Sim | I37: - | J37: Joana Ñato | K37: Financeiro | L37: comexuio@paraiso.com.ec | M37: +593 99 784 7907 | N37: pagamento
A38: Equador | B38: Guayaquil | C38: Productos Paraiso do Ecuador | D38: Sim | E38: - | F38: - | G38: Grande | H38: Sim | I38: - | J38: Maria José Camacho | K38: Comex | L38: comexgye@paraiso.com.ec | M38: +593 99 949 4115
A39: Equador | B39: Guayaquil | C39: Productos Paraiso do Ecuador | D39: Sim | E39: - | F39: - | G39: Grande | H39: Sim | I39: - | J39: René Cortes | K39: Gerente Gral | L39: gerenciagye@paraiso.com.ec | M39: +593 99 377 7690 | N39: pagamento
A40: Equador | B40: Cuenca | C40: Colineal | D40: Sim | E40: - | F40: - | G40: Medio | H40: - | I40: - | J40: Gabriela Briones | K40: Marketing | L40: gabrielabriones@colinealcorp.com | M40: +593 99 530 6517
A41: Equador | B41: Cuenca | C41: Colineal | D41: Sim | E41: - | F41: - | G41: Medio | H41: - | I41: - | J41: Patricio Culquer | K41: Compras | L41: patricioculquer@colinealcorp.com | M41: +593 99 847 9284
A42: Equador | B42: Cuenca | C42: Colineal | D42: Sim | E42: - | F42: - | G42: Medio | H42: - | I42: - | J42: Patricia Arce | K42: Comex | L42: importaciones@colinealcorp.com | M42: +593 99 151 9067
A43: Bolivia | B43: Santa Cruz | C43: Maxi King | D43: Sim | E43: - | F43: - | G43: Grande | H43: - | I43: - | J43: Claudia Siles | K43: Comex | L43: importaciones@maxiking.com.bo | M43: +591 75002325 | N43: pagamento
A44: Bolivia | B44: Santa Cruz | C44: Maxi King | D44: Sim | E44: - | F44: - | G44: Grande | H44: - | I44: - | J44: Livio Zozzoli | K44: Socio | L44: liviozozzoli@maxiking.com.bo | M44: +591 76640034
A45: Bolivia | B45: Santa Cruz | C45: Maxi King | D45: Sim | E45: - | F45: - | G45: Grande | H45: - | I45: - | J45: Silvia Zerda | K45: Socio | L45: silviazerda@maxiking.com.bo | M45: +591 76640036
A46: Bolivia | B46: Santa Cruz | C46: Maxi King | D46: Sim | J46: Liliana Jare Arias | K46: Administrativo | L46: contabilidad@maxiking.com.bo | M46: +591 33485151 | N46: cuida de transporte asignado
A47: Bolivia | B47: Santa Cruz | C47: Heaven (David Moreno) | D47: Sim | E47: - | F47: - | G47: Pequeno | H47: - | I47: - | J47: Severiano Melgar | K47: Financeiro | L47: jefecompras@colchonesheaven.com | M47: +591 78516162
A48: Bolivia | B48: Santa Cruz | C48: Heaven (David Moreno) | D48: Sim | E48: - | F48: - | G48: Pequeno | H48: - | I48: - | J48: David Moreno | K48: Socio | L48: david_moreno_2000@yahoo.com | M48: +591 70871171 | N48: compras@colchonesheaven.com
A49: Bolivia | B49: Santa Cruz | C49: Heaven (David Moreno) | D49: Sim | E49: - | F49: - | G49: Pequeno | H49: - | I49: - | J49: Daniel Garnica | K49: Compras | L49: david_moreno_2000@yahoo.com | M49: +591 75501534
A50: Bolivia | B50: Santa Cruz | C50: Heaven (David Moreno) | D50: Sim | E50: - | F50: - | G50: Pequeno | H50: - | I50: - | J50: Siro | K50: Compras | L50: siro22091975@gmail.com | M50: +591 67898756
A51: Bolivia | B51: Santa Cruz | C51: Wenturs Trade (Distribuidor) | D51: Sim | E51: - | F51: - | G51: Pequeno | H51: - | I51: - | J51: Sr. Josimar Kronembold | K51: Socio | L51: josimar.vicunha@gmail.com | M51: +591 75381793
A52: Bolivia | B52: Santa Cruz | C52: Wenturs Trade (Distribuidor) | D52: Sim | E52: - | F52: - | G52: Pequeno | H52: - | I52: - | J52: Arnaldo Balcazar | K52: Socio | L52: NA | M52: +591 69050221
A53: Venezuela | B53: Valencia | C53: Corporacion CLC (Colchones CLC) | D53: Sim | E53: - | F53: - | G53: Grande | H53: - | I53: - | J53: Jasmin Dugga | K53: Compras | L53: j.dugga@clccolchones.com | M53: +58 412-8317925
A54: Colombia | B54: Medellin | C54: Comodisimos (Espumas Plasticas) | D54: Sim | E54: - | F54: - | G54: Grande | H54: Sim | I54: - | J54: Manuela Torres | K54: Compras | L54: manuela.torres@comodisimos.com | M54: +57 311 7282925
A55: Colombia | B55: Medellin | C55: Comodisimos (Espumas Plasticas) | D55: Sim | E55: - | F55: - | G55: Grande | H55: Sim | I55: - | J55: Veronica Ardila | K55: Marketing | L55: veronica.ardila@comodisimos.com | M55: +57 300 2422425
A56: Guatemala | B56: Guatemala | C56: Facenco | D56: Sim | E56: - | F56: - | G56: Grande | H56: Sim | I56: Sim | J56: Nestor Alvarado | K56: Compras | L56: coordinadorcompras@camasfacenco.net | M56: +502 5191 1018
A57: Guatemala | B57: Guatemala | C57: Facenco | D57: Sim | E57: - | F57: - | G57: Grande | H57: Sim | I57: Sim | J57: Mishell Fernandez | K57: Marketing | L57: coordinadorcompras@camasfacenco.net | M57: +502 5525 8000
A58: Guatemala | B58: Guatemala | C58: Facenco | D58: Sim | E58: - | F58: - | G58: Grande | H58: Sim | I58: Sim | J58: Rudy Fuentes | K58: Vendas | L58: rfuentes@camasfacenco.net | M58: +502 5702 8641 | N58: Dir. Comercial / Socio
A59: Guatemala | B59: Guatemala | C59: Industria Ultra | D59: Sim | E59: - | F59: - | G59: Medio | H59: - | I59: - | J59: Juan Solares | K59: Socio | L59: jpsolares@ultraindustrias.com | M59: +502 5306 1895
A60: Guatemala | B60: Guatemala | C60: Industria Ultra | D60: Sim | E60: - | F60: - | G60: Medio | H60: - | I60: - | J60: Luis Pedro Solares | K60: Socio | L60: luispsolares@ultraindustrias.com | M60: +502 5204 8138
A61: Guatemala | B61: Guatemala | C61: Camas Florida | D61: Sim | E61: - | F61: - | G61: Grande | H61: - | I61: - | J61: Annie Mejia | K61: Compras | L61: compras.hn@industriasflorida.com | M61: +504 3151-3705
A62: Guatemala | B62: Guatemala | C62: Camas Florida | D62: Sim | E62: - | F62: - | G62: Grande | H62: - | I62: - | J62: Jacqueline Centeno | K62: Compras | L62: compras@industriasflorida.com | M62: +502 4570 7194
A63: Honduras | B63: Tegucigalpa | C63: Proahfoam | D63: Sim | E63: - | F63: - | G63: Medio | H63: - | I63: - | J63: Arturo Castillo | K63: Socio | L63: acastillo@prohfoam.com | M63: +504 9990-8010
A64: Honduras | B64: Tegucigalpa | C64: Proahfoam | D64: Sim | E64: - | F64: - | G64: Medio | H64: - | I64: - | J64: Mariela Aguilar | K64: Compras | L64: compras@prohfoam.com | M64: +504 9443-2161
A65: Honduras | B65: Tegucigalpa | C65: Camas Florida | D65: Sim | E65: - | F65: - | G65: Medio | H65: - | I65: - | J65: Claudia Acosta | K65: Comex | L65: gerenciadelogistica.hn@industriasflorida.com | M65: +504 3157-3432
A66: Cuba | B66: Mariel | C66: Sueños Tropicales (AGT) | D66: Sim | E66: - | F66: - | G66: Grande | H66: - | I66: - | J66: Neorquides Hernández | K66: Representante | L66: neorquidessag@gmail.com | M66: +34 641 91 60 94 | N66: Komfort Cuba
A67: Cuba | B67: Mariel | C67: Sueños Tropicales (AGT) | D67: Sim | E67: - | F67: - | G67: Grande | H67: - | I67: - | J67: Ricardo | K67: Socio | L67: NA | M67: +53 5 2639277
A68: Cuba | B68: Mariel | C68: Sueños Tropicales (AGT) | D68: Sim | E68: - | F68: - | G68: Grande | H68: - | I68: - | J68: Walter Castro | K68: Financeiro | L68: waltercastrosuarez@gmail.com | M68: +1 (809) 224-3758

Sheet BANKING DATA CONEXAO MALHAS
